Workbook

Sheet cashflow
A1: Finance >>Cash Flow (Standalone)>>Dabur India Ltd(Curr. Rs in )
A2: Year | B2: 202503 | C2: 202403 | D2: 202303 | E2: 202203 | F2: 202103 | G2: 202003 | H2: 201903 | I2: 201803 | J2: 201703 | K2: 201603
A3: Cash Flow Summary
A4: Cash and Cash Equivalents at Beginning of the year | B4: 10.77 | C4: 15.35 | D4: 10.47 | E4: 7.01 | F4: -21.75 | G4: -20.24 | H4: 57.8 | I4: -1.25 | J4: 24.41 | K4: 13.49
A5: Net Cash from Operating Activities | B5: 1622.97 | C5: 1653.33 | D5: 1561.91 | E5: 1319.95 | F5: 1704.17 | G5: 1154.77 | H5: 1123.57 | I5: 816.41 | J5: 926.94 | K5: 960.3
A6: Net Profit before Tax & Extraordinary Items | B6: 1808.34 | C6: 1966.7 | D6: 1828.67 | E6: 1896.31 | F6: 1683.31 | G6: 1408.47 | H6: 1503.35 | I6: 1373.13 | J6: 1294.35 | K6: 1209.35
A7: Depreciation | B7: 250.93 | C7: 208.86 | D7: 188.29 | E7: 160.39 | F7: 143.4 | G7: 129.93 | H7: 108.83 | I7: 102.5 | J7: 75.43 | K7: 72.83
A8: Interest (Net) | B8: -205.45 | C8: -236.1 | D8: -251.66 | E8: -248.27 | F8: -213.09 | G8: -196.35 | H8: -202.77 | I8: -200.44 | J8: -187.91 | K8: -151.07
A9: Dividend Received | B9: 0 | C9: 0 | D9: 0 | E9: 0 | F9: 0 | G9: 0 | H9: 0 | I9: 0 | J9: 0 | K9: 0
A10: P/L on Sales of Assets | B10: 1.27 | C10: 1.34 | D10: -16.53 | E10: 0.68 | F10: -0.33 | G10: 1.76 | H10: -0.89 | I10: -2.42 | J10: 0.86 | K10: -3.78
A11: P/L on Sales of Invest | B11: 0 | C11: 0 | D11: 0 | E11: 0 | F11: -0.42 | G11: 0 | H11: 0 | I11: 0 | J11: 0 | K11: -21.53
A12: Prov. & W/O (Net) | B12: 13.25 | C12: 25.67 | D12: 9.73 | E12: -8.7 | F12: 22.82 | G12: 14.98 | H12: 11.44 | I12: 14.87 | J12: 9.46 | K12: 7.38
A13: P/L in Forex | B13: 2.57 | C13: -0.02 | D13: 0.05 | E13: -1.24 | F13: 1.11 | G13: -3.7 | H13: 2.93 | I13: 1.77 | J13: 0.87 | K13: 2.14
A14: Fin. Lease & Rental Chrgs | B14: 0 | C14: 0 | D14: 0 | E14: 0 | F14: 0 | G14: 0 | H14: 0 | I14: 0 | J14: 0 | K14: 0
A15: Others | B15: -91.82 | C15: -12.13 | D15: 54.28 | E15: 14 | F15: 7.41 | G15: 109.68 | H15: 55.07 | I15: -18.63 | J15: -46.19 | K15: 45
... A60: Cash and Cash Equivalents at End of the year | B60: 24.16 | C60: 10.77 | D60: 15.35 | E60: 10.47 | F60: 7.01 | G60: -21.75 | H60: -20.24 | I60: 57.8 | J60: -1.25 | K60: 24.42

Sheet Bal.sheet
A1: Finance >>Balance Sheet (Standalone)>>Dabur India Ltd(Curr. in )
A2: Year | B2: 201603 | C2: 201703 | D2: 201803 | E2: 201903 | F2: 202003 | G2: 202103 | H2: 202203 | I2: 202303 | J2: 202403 | K2: 202503
A3: SOURCES OF FUNDS :
A4: Share Capital | B4: 175.91 | C4: 176.15 | D4: 176.15 | E4: 176.63 | F4: 176.71 | G4: 176.74 | H4: 176.79 | I4: 177.18 | J4: 177.2 | K4: 177.23
A5: Reserves Total | B5: 2918.38 | C5: 3481.73 | D5: 4050.71 | E5: 3792.19 | F5: 4397.52 | G5: 5214.48 | H5: 5687.08 | I5: 6109.7 | J5: 6738.17 | K5: 7246.06
A8: Total Shareholders Funds | B8: 3094.29 | C8: 3657.88 | D8: 4226.86 | E8: 3968.82 | F8: 4574.23 | G8: 5391.22 | H8: 5863.87 | I8: 6286.88 | J8: 6915.37 | K8: 7423.29
A9: Secured Loans | B9: 7.68 | C9: 209.07 | D9: 208.6 | E9: 227.73 | F9: 101.19 | G9: 26.94 | H9: 0 | I9: 177.76 | J9: 99.99 | K9: 0.1
A10: Unsecured Loans | B10: 79.55 | C10: 74.68 | D10: 78.01 | E10: 82.13 | F10: 49.46 | G10: 152.93 | H10: 560.18 | I10: 437.7 | J10: 675.97 | K10: 378.62
A11: Total Debt | B11: 87.23 | C11: 283.75 | D11: 286.61 | E11: 309.86 | F11: 150.65 | G11: 179.87 | H11: 560.18 | I11: 615.46 | J11: 775.96 | K11: 378.72
A12: Other Liabilities | B12: 49.99 | C12: 51.23 | D12: 54.29 | E12: 57.32 | F12: 59.35 | G12: 56.92 | H12: 60.82 | I12: 62.62 | J12: 65.63 | K12: 64.49
A13: Total Liabilities | B13: 3231.51 | C13: 3992.86 | D13: 4567.76 | E13: 4336 | F13: 4784.23 | G13: 5628.01 | H13: 6484.87 | I13: 6964.96 | J13: 7756.96 | K13: 7866.5
A14: APPLICATION OF FUNDS :
A15: Gross Block | B15: 1131.34 | C15: 1549.58 | D15: 1671.38 | E15: 1774.43 | F15: 1982.29 | G15: 2168.03 | H15: 2501.1 | I15: 2937.65 | J15: 3345.31 | K15: 3722.26
A16: Less : Accumulated Depreciation | B16: 492.53 | C16: 556.25 | D16: 640.9 | E16: 737.81 | F16: 848.01 | G16: 963.22 | H16: 1102.1 | I16: 1275.68 | J16: 1467.11 | K16: 1686.64
A17: Less:Impairment of Assets | B17: 0 | C17: 0 | D17: 0 | E17: 0 | F17: 0 | G17: 0 | H17: 0 | I17: 0 | J17: 0 | K17: 0
A18: Net Block | B18: 638.81 | C18: 993.33 | D18: 1030.48 | E18: 1036.62 | F18: 1134.28 | G18: 1204.81 | H18: 1399 | I18: 1661.97 | J18: 1878.2 | K18: 2035.62
A21: Capital Work in Progress | B21: 24.96 | C21: 28.25 | D21: 26.82 | E21: 21.69 | F21: 105.83 | G21: 107.26 | H21: 128.48 | I21: 109.43 | J21: 184.23 | K21: 136.88
A22: Producing Properties | B22: 0 | C22: 0 | D22: 0 | E22: 0 | F22: 0 | G22: 0 | H22: 0 | I22: 0 | J22: 0 | K22: 0
A23: Investments | B23: 2570.31 | C23: 3054.15 | D23: 3433.06 | E23: 2962.14 | F23: 2466.83 | G23: 3573.9 | H23: 5007.08 | I23: 5475.05 | J23: 6148.47 | K23: 6358.82
A24: Current Assets, Loans & Advances
A25: Inventories | B25: 615.56 | C25: 599.27 | D25: 704.79 | E25: 732.9 | F25: 809.14 | G25: 1114.16 | H25: 1237.96 | I25: 1223.77 | J25: 1149.88 | K25: 1288.07
A26: Sundry Debtors | B26: 420.69 | C26: 333.25 | D26: 321.34 | E26: 431.46 | F26: 379.63 | G26: 281.24 | H26: 454.55 | I26: 561.18 | J26: 719.21 | K26: 600.58
A27: Cash and Bank | B27: 55.63 | C27: 26.16 | D27: 87.02 | E27: 124.71 | F27: 525.6 | G27: 834.74 | H27: 136.18 | I27: 33.4 | J27: 71.11 | K27: 133.02
A28: Loans and Advances | B28: 68.26 | C28: 91.81 | D28: 132.3 | E28: 109.88 | F28: 168.15 | G28: 148.71 | H28: 126.06 | I28: 140.4 | J28: 232 | K28: 280.07
A29: Total Current Assets | B29: 1160.14 | C29: 1050.49 | D29: 1245.45 | E29: 1398.95 | F29: 1882.52 | G29: 2378.85 | H29: 1954.75 | I29: 1958.75 | J29: 2172.2 | K29: 2301.74
A30: Less : Current Liabilities and Provisions | U30: 1003.15 | V30: 971.62 | W30: 937.19 | X30: 789.76
A31: Current Liabilities | B31: 1070.85 | C31: 1061.37 | D31: 1080.62 | E31: 1145.54 | F31: 1188.38 | G31: 1715.09 | H31: 1844.16 | I31: 2108.21 | J31: 2396.79 | K31: 2663.03 | U31: 998.32 | V31: 960.62 | W31: 914.52 | X31: 784.88
A32: Provisions | B32: 50.85 | C32: 64.51 | D32: 68.29 | E32: 88.92 | F32: 127.5 | G32: 161.06 | H32: 192.93 | I32: 202.51 | J32: 278.56 | K32: 342.69 | U32: 4.83 | V32: 11 | W32: 22.67 | X32: 4.88
A33: Total Current Liabilities | B33: 1121.7 | C33: 1125.88 | D33: 1148.91 | E33: 1234.46 | F33: 1315.88 | G33: 1876.15 | H33: 2037.09 | I33: 2310.72 | J33: 2675.35 | K33: 3005.72 | U33: 0 | V33: 0 | W33: 0 | X33: 0
A34: Net Current Assets | B34: 38.44 | C34: -75.39 | D34: 96.54 | E34: 164.49 | F34: 566.64 | G34: 502.7 | H34: -82.34 | I34: -351.97 | J34: -503.15 | K34: -703.98 | U34: 0 | V34: 0 | W34: 0 | X34: 0
U35: 0 | V35: 0 | W35: 0 | X35: 146.46
A36: Deferred Tax Assets | B36: 13.22 | C36: 5.79 | D36: 17.8 | E36: 102.61 | F36: 151.29 | G36: 148.95 | H36: 78.32 | I36: 100.24 | J36: 103.66 | K36: 89.68 | U36: 0 | V36: 0 | W36: 0 | X36: 0
A37: Deferred Tax Liability | B37: 89.74 | C37: 104.07 | D37: 113.83 | E37: 110.93 | F37: 129.67 | G37: 131.5 | H37: 148.36 | I37: 177 | J37: 204.16 | K37: 222.93 | U37: 0 | V37: 0 | W37: 0 | X37: 0
A38: Net Deferred Tax | B38: -76.52 | C38: -98.28 | D38: -96.03 | E38: -8.32 | F38: 21.62 | G38: 17.45 | H38: -70.04 | I38: -76.76 | J38: -100.5 | K38: -133.25 | U38: 0 | V38: 0 | W38: 0 | X38: 0
A39: Other Assets | B39: 35.51 | C39: 90.8 | D39: 76.89 | E39: 159.38 | F39: 489.03 | G39: 221.89 | H39: 102.69 | I39: 147.24 | J39: 149.71 | K39: 172.41 | U39: 19.7 | V39: 12.79 | W39: 12.32 | X39: 7.24
A40: Long-Term Loans and Advances | B40: 33.97 | C40: 16.2 | D40: 22.8 | E40: 91.64 | F40: 420.91 | G40: 108.99 | H40: 23.15 | I40: 75.48 | J40: 56.98 | K40: 40.91 | U40: 0 | V40: 0 | W40: 0 | X40: 0
A41: Other Non-Current Assets | B41: 1.54 | C41: 74.6 | D41: 54.09 | E41: 67.74 | F41: 68.12 | G41: 112.9 | H41: 79.51 | I41: 71.76 | J41: 92.73 | K41: 131.5 | U41: 0.91 | V41: 1.41 | W41: 2.1 | X41: 0.87
A42: Others | B42: 0 | C42: 0 | D42: 0 | E42: 0 | F42: 0 | G42: 0 | H42: 0.03 | I42: 0 | J42: 0 | K42: 0 | U42: 9.47 | V42: 6.56 | W42: 6.35 | X42: 5.7
A43: Total Assets | B43: 3231.51 | C43: 3992.86 | D43: 4567.76 | E43: 4336 | F43: 4784.23 | G43: 5628.01 | H43: 6484.87 | I43: 6964.96 | J43: 7756.96 | K43: 7866.5 | U43: 0.89 | V43: 0.93 | W43: 0.75 | X43: 0
A44: Contingent Liabilities | B44: 1183.31 | C44: 1055.31 | D44: 846.63 | E44: 536.74 | F44: 222.88 | G44: 241.7 | H44: 253.92 | I44: 248.38 | J44: 221.08 | K44: 562.3 | U44: 111.42 | V44: 87.31 | W44: 102.66 | X44: 120.82

Sheet PL
A1: Finance >>Profit & Loss (Standalone)>>Dabur India Ltd(Curr. in )
A2: Year | B2: 202503 | C2: 202403 | D2: 202303 | E2: 202203 | F2: 202103 | G2: 202003 | H2: 201903 | I2: 201803 | J2: 201703 | K2: 201603
A3: INCOME :
A4: Sales Turnover | B4: 9070.71 | C4: 9135.6 | D4: 8684.35 | E4: 8179.5 | F4: 7184.73 | G4: 6309.8 | H4: 6273.19 | I4: 5609.06 | J4: 5369.84 | K4: 5422.57
A5: Net Sales | B5: 9070.71 | C5: 9135.6 | D5: 8684.35 | E5: 8179.5 | F5: 7184.73 | G5: 6309.8 | H5: 6273.19 | I5: 5592.29 | J5: 5290.65 | K5: 5340.04
A6: Other Income | B6: 451.94 | C6: 417.62 | D6: 392.17 | E6: 341.55 | F6: 276.65 | G6: 276.9 | H6: 274.74 | I6: 283.23 | J6: 274.64 | K6: 194.36
A7: Stock Adjustments | B7: -12.9 | C7: -49.18 | D7: 24.98 | E7: 28.49 | F7: 176.71 | G7: 69.89 | H7: -10.09 | I7: 74.03 | J7: 8.19 | K7: 23.77
A8: Total Income | B8: 9509.75 | C8: 9504.04 | D8: 9101.5 | E8: 8549.54 | F8: 7638.09 | G8: 6656.59 | H8: 6537.84 | I8: 5949.55 | J8: 5573.48 | K8: 5558.17
A9: EXPENDITURE :
A10: Raw Materials | B10: 3896.24 | C10: 3797.27 | D10: 3797.74 | E10: 3444.55 | F10: 3065.28 | G10: 2531.18 | H10: 2511.23 | I10: 2281.22 | J10: 2129.17 | K10: 2150.59
A11: Power & Fuel Cost | B11: 97.85 | C11: 99.23 | D11: 93.32 | E11: 85.02 | F11: 70.72 | G11: 66.48 | H11: 63.99 | I11: 59.43 | J11: 50.61 | K11: 47.77
A12: Employee Cost | B12: 776.86 | C12: 782.14 | D12: 725.96 | E12: 678.71 | F12: 655.82 | G12: 578.26 | H12: 572.33 | I12: 461.13 | J12: 425.3 | K12: 431.89
A13: Other Manufacturing Expenses | B13: 1165.16 | C13: 1192.6 | D13: 1199.1 | E13: 1049.95 | F13: 880.46 | G13: 854.86 | H13: 804.04 | I13: 756.51 | J13: 732.62 | K13: 716.49
A14: Selling and Administration Expenses | B14: 1267.24 | C14: 1228.56 | D14: 1021.29 | E14: 1068.62 | F14: 1002.15 | G14: 847.58 | H14: 835 | I14: 776.29 | J14: 748.55 | K14: 733.72
A15: Miscellaneous Expenses | B15: 147.55 | C15: 147.54 | D15: 200.76 | E15: 147.32 | F15: 127.81 | G15: 220.56 | H15: 109.27 | I15: 117.45 | J15: 101.22 | K15: 185.27
A17: Total Expenditure | B17: 7350.9 | C17: 7247.34 | D17: 7038.17 | E17: 6474.17 | F17: 5802.24 | G17: 5098.92 | H17: 4895.86 | I17: 4452.03 | J17: 4187.47 | K17: 4265.73
A18: Operating Profit | B18: 2158.85 | C18: 2256.7 | D18: 2063.33 | E18: 2075.37 | F18: 1835.85 | G18: 1557.67 | H18: 1641.98 | I18: 1497.52 | J18: 1386.01 | K18: 1292.44
A19: Interest | B19: 99.58 | C19: 81.14 | D19: 46.37 | E19: 18.67 | F19: 9.14 | G19: 19.27 | H19: 29.8 | I19: 21.89 | J19: 16.23 | K19: 10.26
A20: Gross Profit | B20: 2059.27 | C20: 2175.56 | D20: 2016.96 | E20: 2056.7 | F20: 1826.71 | G20: 1538.4 | H20: 1612.18 | I20: 1475.63 | J20: 1369.78 | K20: 1282.18
A21: Depreciation | B21: 250.93 | C21: 208.86 | D21: 188.29 | E21: 160.39 | F21: 143.4 | G21: 129.93 | H21: 108.83 | I21: 102.5 | J21: 75.43 | K21: 72.83
A22: Profit Before Tax | B22: 1808.34 | C22: 1966.7 | D22: 1828.67 | E22: 1896.31 | F22: 1683.31 | G22: 1408.47 | H22: 1503.35 | I22: 1373.13 | J22: 1294.35 | K22: 1209.35
... A42: Dividend Per Share Adj.(Rs) | B42: 8 | C42: 5.5 | D42: 5.2 | E42: 5.2 | F42: 4.75 | G42: 3 | H42: 2.75 | I42: 7.5 | J42: 2.25 | K42: 2.25

Sheet sources
A3: 1 | B3: Actual Financial Statement data for last 5 years
B4: Revenue Growth | C4: 0.013 | D4: As mentioned in Annual Report 2025 | E4: chrome-extension://efaidnbmnnnibpcajpcglclefindmkaj/https://www.dabur.com/Investors/Financial%20Information/Reports/Annual%20Reports/2024-25/Dabur%20India%20Limited%20Annual%20Report%202024-25.pdf?utm_
A5: 2 | B5: Tax Rate | C5: 0.3494 | D5: As mentioned in Annual Report 2025 | E5: chrome-extension://efaidnbmnnnibpcajpcglclefindmkaj/https://www.dabur.com/Investors/Financial%20Information/Reports/Annual%20Reports/2024-25/Dabur%20India%20Limited%20Annual%20Report%202024-25.pdf?utm_
A6: 3 | B6: Data period used for Stock and Market Index Price
A7: 4 | B7: Risk Free Rate | C7: 0.0737
A8: 5 | B8: Market Risk Premium
A9: 6 | B9: Perpetuity Growth Rate for Terminal Value
A10: 7 | B10: Basis for selection of peer companies
A11: 8 | B11: Sensitivity Analysis
A12: 9 | B12: Peer Comparison

Sheet Assumption
E1: Forecasted Income Statement
A3: Year | B3: 2016 | C3: 2017 | D3: 2018 | E3: 2019 | F3: 2020 | G3: 2021 | H3: 2022 | I3: 2023 | J3: 2024 | K3: 2025 | L3: 2026 | M3: 2027 | N3: 2028 | O3: 2029 | P3: 2030 | Q3: YOY
A4: INCOME :
A5: Sales Turnover | B5: 5422.57 | C5: 5369.84 | D5: 5609.06 | E5: 6273.19 | F5: 6309.8 | G5: 7184.73 | H5: 8179.5 | I5: 8684.35 | J5: 9135.6 | K5: 9070.71 | L5: =K5*(1+$Q$9) -> 9609.8811 | M5: =L5*(1+$Q$9) -> 10181.101 | N5: =M5*(1+$Q$9) -> 10786.275 | O5: =N5*(1+$Q$9) -> 11427.421 | P5: =O5*(1+$Q$9) -> 12106.677
A6: Stock Adjustments | B6: 23.77 | C6: 8.19 | D6: 74.03 | E6: -10.09 | F6: 69.89 | G6: 176.71 | H6: 28.49 | I6: 24.98 | J6: -49.18 | K6: -12.9
A7: Net Sales | B7: =SUM(B5:B6) -> 5446.34 | C7: =SUM(C5:C6) -> 5378.03 | D7: =SUM(D5:D6) -> 5683.09 | E7: =SUM(E5:E6) -> 6263.1 | F7: =SUM(F5:F6) -> 6379.69 | G7: =SUM(G5:G6) -> 7361.44 | H7: =SUM(H5:H6) -> 8207.99 | I7: =SUM(I5:I6) -> 8709.33 | ... K7: =SUM(K5:K6) -> 9057.81 | L7: =L5+L6 -> 9609.8811 | M7: =M5+M6 -> 10181.101 | N7: =N5+N6 -> 10786.275 | O7: =O5+O6 -> 11427.421 | P7: =P5+P6 -> 12106.677
A8: Total Income | B8: =B7 -> 5446.34 | C8: =C7 -> 5378.03 | D8: =D7 -> 5683.09 | E8: =E7 -> 6263.1 | F8: =F7 -> 6379.69 | G8: =G7 -> 7361.44 | H8: =H7 -> 8207.99 | I8: =I7 -> 8709.33 | ... K8: =K7 -> 9057.81 | L8: =K8*(1+$Q$9) -> 9596.2143 | M8: =L8*(1+$Q$9) -> 10166.622 | N8: =M8*(1+$Q$9) -> 10770.935 | O8: =N8*(1+$Q$9) -> 11411.169 | P8: =O8*(1+$Q$9) -> 12089.459
A9: YOY | C9: =(C8-B8)/B8 -> -0.012542368 | D9: =(D8-C8)/C8 -> 0.056723373 | E9: =(E8-D8)/D8 -> 0.10205892 | F9: =(F8-E8)/E8 -> 0.018615382 | G9: =(G8-F8)/F8 -> 0.15388679 | H9: =(H8-G8)/G8 -> 0.11499788 | I9: =(I8-H8)/H8 -> 0.061079509 | J9: =(J8-I8)/I8 -> 0.043297246 | K9: =(K8-J8)/J8 -> -0.0031486548 | Q9: =AVERAGE(C9:K9) -> 0.059440897 | R9: Average
A10: Raw Materials | B10: 2150.59 | C10: 2129.17 | D10: 2281.22 | E10: 2511.23 | F10: 2531.18 | G10: 3065.28 | H10: 3444.55 | I10: 3797.74 | J10: 3797.27 | K10: 3896.24 | L10: =K10*(1+$Q$16) -> 4154.89 | M10: =L10*(1+$Q$16) -> 4430.7104 | N10: =M10*(1+$Q$16) -> 4724.8409 | O10: =N10*(1+$Q$16) -> 5038.4972 | P10: =O10*(1+$Q$16) -> 5372.9754
A11: Power & Fuel Cost | B11: 47.77 | C11: 50.61 | D11: 59.43 | E11: 63.99 | F11: 66.48 | G11: 70.72 | H11: 85.02 | I11: 93.32 | J11: 99.23 | K11: 97.85 | L11: =K11*(1+$Q$16) -> 104.34572 | M11: =L11*(1+$Q$16) -> 111.27267 | N11: =M11*(1+$Q$16) -> 118.65945 | O11: =N11*(1+$Q$16) -> 126.5366 | P11: =O11*(1+$Q$16) -> 134.93667
A12: Employee Cost | B12: 431.89 | C12: 425.3 | D12: 461.13 | E12: 572.33 | F12: 578.26 | G12: 655.82 | H12: 678.71 | I12: 725.96 | J12: 782.14 | K12: 776.86 | L12: =K12*(1+$Q$16) -> 828.43147 | M12: =L12*(1+$Q$16) -> 883.4265 | N12: =M12*(1+$Q$16) -> 942.07234 | O12: =N12*(1+$Q$16) -> 1004.6114 | P12: =O12*(1+$Q$16) -> 1071.302
A13: Other Manufacturing Expenses | B13: 716.49 | C13: 732.62 | D13: 756.51 | E13: 804.04 | F13: 854.86 | G13: 880.46 | H13: 1049.95 | I13: 1199.1 | J13: 1192.6 | K13: 1165.16 | L13: =K13*(1+$Q$16) -> 1242.5086 | M13: =L13*(1+$Q$16) -> 1324.9919 | N13: =M13*(1+$Q$16) -> 1412.9509 | O13: =N13*(1+$Q$16) -> 1506.7489 | P13: =O13*(1+$Q$16) -> 1606.7737
A14: Selling and Administration Expenses | B14: 733.72 | C14: 748.55 | D14: 776.29 | E14: 835 | F14: 847.58 | G14: 1002.15 | H14: 1068.62 | I14: 1021.29 | J14: 1228.56 | K14: 1267.24 | L14: =K14*(1+$Q$16) -> 1351.3651 | M14: =L14*(1+$Q$16) -> 1441.0748 | N14: =M14*(1+$Q$16) -> 1536.7399 | O14: =N14*(1+$Q$16) -> 1638.7556 | P14: =O14*(1+$Q$16) -> 1747.5436
A15: Total Expenditure | B15: =SUM(B10:B14) -> 4080.46 | C15: =SUM(C10:C14) -> 4086.25 | D15: =SUM(D10:D14) -> 4334.58 | E15: =SUM(E10:E14) -> 4786.59 | F15: =SUM(F10:F14) -> 4878.36 | G15: =SUM(G10:G14) -> 5674.43 | H15: =SUM(H10:H14) -> 6326.85 | I15: =SUM(I10:I14) -> 6837.41 | ... K15: =SUM(K10:K14) -> 7203.35 | L15: =K15*(1+$Q$16) -> 7681.5409 | M15: =L15*(1+$Q$16) -> 8191.4763 | N15: =M15*(1+$Q$16) -> 8735.2635 | O15: =N15*(1+$Q$16) -> 9315.1497 | P15: =O15*(1+$Q$16) -> 9933.5314
A16: YOY | C16: =(C15-B15)/B15 -> 0.0014189577 | D16: =(D15-C15)/C15 -> 0.060772102 | E16: =(E15-D15)/D15 -> 0.10428 | F16: =(F15-E15)/E15 -> 0.019172313 | G16: =(G15-F15)/F15 -> 0.16318394 | H16: =(H15-G15)/G15 -> 0.11497542 | I16: =(I15-H15)/H15 -> 0.080697345 | J16: =(J15-I15)/I15 -> 0.038375642 | K16: =(K15-J15)/J15 -> 0.014584918 | Q16: =AVERAGE(C16:K16) -> 0.066384516 | R16: Average
A17: Operating Profit | B17: =B8-B15 -> 1365.88 | C17: =C8-C15 -> 1291.78 | D17: =D8-D15 -> 1348.51 | E17: =E8-E15 -> 1476.51 | F17: =F8-F15 -> 1501.33 | G17: =G8-G15 -> 1687.01 | H17: =H8-H15 -> 1881.14 | I17: =I8-I15 -> 1871.92 | ... K17: =K8-K15 -> 1854.46 | L17: =K17*(1+$Q$18) -> 1922.4554 | M17: =L17*(1+$Q$18) -> 1992.9439 | N17: =M17*(1+$Q$18) -> 2066.017 | O17: =N17*(1+$Q$18) -> 2141.7693 | P17: =O17*(1+$Q$18) -> 2220.2992
A18: YOY | C18: =(C17-B17)/B17 -> -0.054250739 | D18: =(D17-C17)/C17 -> 0.043916147 | E18: =(E17-D17)/D17 -> 0.094919578 | F18: =(F17-E17)/E17 -> 0.01680991 | G18: =(G17-F17)/F17 -> 0.12367701 | H18: =(H17-G17)/G17 -> 0.11507341 | I18: =(I17-H17)/H17 -> -0.0049012833 | J18: =(J17-I17)/I17 -> 0.061273986 | K18: =(K17-J17)/J17 -> -0.066525053 | Q18: =AVERAGE(C18:K18) -> 0.036665885 | AC18: ..0320
A19: Interest | B19: 10.26 | C19: 16.23 | D19: 21.89 | E19: 29.8 | F19: 19.27 | G19: 9.14 | H19: 18.67 | I19: 46.37 | J19: 81.14 | K19: 99.58 | L19: =K19*(1+$Q$20) -> 142.91224 | M19: =L19*(1+$Q$20) -> 205.1005 | N19: =M19*(1+$Q$20) -> 294.34999 | O19: =N19*(1+$Q$20) -> 422.43639 | P19: =O19*(1+$Q$20) -> 606.2596
A20: YOY | C20: =(C19-B19)/B19 -> 0.58187135 | D20: =(D19-C19)/C19 -> 0.34873691 | E20: =(E19-D19)/D19 -> 0.36135222 | F20: =(F19-E19)/E19 -> -0.3533557 | G20: =(G19-F19)/F19 -> -0.5256876 | H20: =(H19-G19)/G19 -> 1.0426696 | I20: =(I19-H19)/H19 -> 1.4836636 | J20: =(J19-I19)/I19 -> 0.74983826 | K20: =(K19-J19)/J19 -> 0.22726152 | Q20: =AVERAGE(C20:K20) -> 0.43515002
A21: Gross Profit | B21: 1282.18 | C21: 1369.78 | D21: 1475.63 | E21: 1612.18 | F21: 1538.4 | G21: 1826.71 | H21: 2056.7 | I21: 2016.96 | J21: 2175.56 | K21: 2059.27 | L21: =K21*(1+$Q$22) -> 2176.3143 | M21: =L21*(1+$Q$22) -> 2300.0112 | N21: =M21*(1+$Q$22) -> 2430.7387 | O21: =N21*(1+$Q$22) -> 2568.8965 | P21: =O21*(1+$Q$22) -> 2714.9068
A22: YOY | C22: =(C21-B21)/B21 -> 0.068321141 | D22: =(D21-C21)/C21 -> 0.077275183 | E22: =(E21-D21)/D21 -> 0.092536747 | F22: =(F21-E21)/E21 -> -0.045764121 | G22: =(G21-F21)/F21 -> 0.187409 | H22: =(H21-G21)/G21 -> 0.12590395 | I22: =(I21-H21)/H21 -> -0.019322215 | J22: =(J21-I21)/I21 -> 0.078633191 | K22: =(K21-J21)/J21 -> -0.053452904 | Q22: =AVERAGE(C22:K22) -> 0.056837774
A23: Depreciation | B23: 72.83 | C23: 75.43 | D23: 102.5 | E23: 108.83 | F23: 129.93 | G23: 143.4 | H23: 160.39 | I23: 188.29 | J23: 208.86 | K23: 250.93 | L23: =K23*(1+$Q$24) -> 288.7643 | M23: =L23*(1+$Q$24) -> 332.30313 | N23: =M23*(1+$Q$24) -> 382.40657 | O23: =N23*(1+$Q$24) -> 440.06443 | P23: =O23*(1+$Q$24) -> 506.41573
A24: YOY | C24: =(C23-B23)/B23 -> 0.035699574 | D24: =(D23-C23)/C23 -> 0.35887578 | E24: =(E23-D23)/D23 -> 0.061756098 | F24: =(F23-E23)/E23 -> 0.19388036 | G24: =(G23-F23)/F23 -> 0.10367121 | H24: =(H23-G23)/G23 -> 0.11847978 | I24: =(I23-H23)/H23 -> 0.17395099 | J24: =(J23-I23)/I23 -> 0.10924638 | K24: =(K23-J23)/J23 -> 0.20142679 | Q24: =AVERAGE(C24:K24) -> 0.15077633
A25: Profit Before Tax | B25: 1209.35 | C25: 1294.35 | D25: 1373.13 | E25: 1503.35 | F25: 1408.47 | G25: 1683.31 | H25: 1896.31 | I25: 1828.67 | J25: 1966.7 | K25: 1808.34 | L25: =L21-L23 -> 1887.55 | M25: =M21-M23 -> 1967.7081 | N25: =N21-N23 -> 2048.3321 | O25: =O21-O23 -> 2128.832 | P25: =P21-P23 -> 2208.4911
A26: Tax | B26: 259.11 | C26: 310.83 | D26: 340.33 | E26: 369.28 | F26: 425.4 | G26: 299.75 | H26: 378.97 | I26: 423.86 | J26: 443.8 | K26: 393.12 | L26: =L25*(1+$Q$27) -> 2322.1906 | M26: =M25*(1+$Q$27) -> 2420.8064 | N26: =N25*(1+$Q$27) -> 2519.9956 | O26: =O25*(1+$Q$27) -> 2619.032 | P26: =P25*(1+$Q$27) -> 2717.0339
A27: Tax rate | B27: =B26/B25 -> 0.21425559 | C27: =C26/C25 -> 0.2401437 | D27: =D26/D25 -> 0.2478498 | E27: =E26/E25 -> 0.24563807 | F27: =F26/F25 -> 0.30202986 | G27: =G26/G25 -> 0.17807178 | H27: =H26/H25 -> 0.19984602 | I27: =I26/I25 -> 0.23178594 | ... K27: =K26/K25 -> 0.21739275 | Q27: =AVERAGE(B27:K27) -> 0.23026707
A28: Deferred Tax | B28: 12.98 | C28: -14.81 | D28: -39.25 | E28: -130.22 | F28: -187.28 | G28: 1.67 | H28: 84.41 | I28: 31.55 | J28: 13.69 | K28: 12 | L28: =K28*(1+$Q$29) -> 77.980492 | M28: =L28*(1+$Q$29) -> 506.74643 | N28: =M28*(1+$Q$29) -> 3293.028 | O28: =N28*(1+$Q$29) -> 21399.329 | P28: =O28*(1+$Q$29) -> 139060.85
A29: YOY | C29: =(C28-B28)/B28 -> -2.1409861 | D29: =(D28-C28)/C28 -> 1.6502363 | E29: =(E28-D28)/D28 -> 2.317707 | F29: =(F28-E28)/E28 -> 0.43818154 | G29: =(G28-F28)/F28 -> -1.0089171 | H29: =(H28-G28)/G28 -> 49.54491 | I29: =(I28-H28)/H28 -> -0.62622912 | J29: =(J28-I28)/I28 -> -0.56608558 | K29: =(K28-J28)/J28 -> -0.12344777 | Q29: =AVERAGE(C29:K29) -> 5.4983744
A30: Reported Net Profit | B30: =B25-B26 -> 950.24 | C30: =C25-C26 -> 983.52 | D30: =D25-D26 -> 1032.8 | E30: =E25-E26 -> 1134.07 | F30: =F25-F26 -> 983.07 | G30: =G25-G26 -> 1383.56 | H30: =H25-H26 -> 1517.34 | I30: =I25-I26 -> 1404.81 | ... K30: =K25-K26 -> 1415.22 | L30: =L25+L26+L28 -> 4287.7211 | M30: =M25+M26+M28 -> 4895.2609 | N30: =N25+N26+N28 -> 7861.3557 | O30: =O25+O26+O28 -> 26147.193 | P30: =P25+P26+P28 -> 143986.38
A31: Extraordinary Items | B31: 20.3 | C31: -0.65 | D31: -9.12 | E31: 0.67 | F31: -69.72 | G31: 0.62 | H31: -0.51 | I31: -9.85 | J31: -1.03 | K31: -0.99 | L31: =K31*(1+$Q$32) -> 7.7645074 | M31: =L31*(1+$Q$32) -> -60.896541 | N31: =M31*(1+$Q$32) -> 477.60772 | O31: =N31*(1+$Q$32) -> -3745.8472 | P31: =O31*(1+$Q$32) -> 29378.443
A32: YOY | C32: =(C31-B31)/B31 -> -1.0320197 | D32: =(D31-C31)/C31 -> 13.030769 | E32: =(E31-D31)/D31 -> -1.0734649 | F32: =(F31-E31)/E31 -> -105.0597 | G32: =(G31-F31)/F31 -> -1.0088927 | H32: =(H31-G31)/G31 -> -1.8225806 | I32: =(I31-H31)/H31 -> 18.313725 | J32: =(J31-I31)/I31 -> -0.89543147 | K32: =(K31-J31)/J31 -> -0.038834951 | Q32: =AVERAGE(C32:K32) -> -8.8429368
A33: Adjusted Net Profit | B33: 916.96 | C33: 998.98 | D33: 1081.17 | E33: 1263.62 | F33: 1240.07 | G33: 1381.27 | H33: 1433.44 | I33: 1383.11 | J33: 1510.24 | K33: 1404.21 | L33: =L30-L31 -> 4279.9566 | M33: =M30-M31 -> 4956.1575 | N33: =N30-N31 -> 7383.748 | O33: =O30-O31 -> 29893.04 | P33: =P30-P31 -> 114607.93
A34: Dividend | B34: 423.2 | C34: 220.19 | D34: 220.19 | E34: 220.79 | F34: 247.39 | G34: 309.3 | H34: 0 | I34: 0 | J34: 0 | K34: 0
A35: YOY | C35: =(C34-B34)/B34 -> -0.47970227 | D35: =(D34-C34)/C34 -> 0 | E35: =(E34-D34)/D34 -> 0.0027249194 | F35: =(F34-E34)/E34 -> 0.12047647 | G35: =(G34-F34)/F34 -> 0.25025264 | H35: =(H34-G34)/G34 -> -1 | I35: =(I34-H34)/H34 -> #DIV/0! | J35: =(J34-I34)/I34 -> #DIV/0! | K35: =(K34-J34)/J34 -> #DIV/0!
A36: RE | B36: =B33-B34 -> 493.76 | C36: =C33-C34 -> 778.79 | D36: =D33-D34 -> 860.98 | E36: =E33-E34 -> 1042.83 | F36: =F33-F34 -> 992.68 | G36: =G33-G34 -> 1071.97 | H36: =H33-H34 -> 1433.44 | I36: =I33-I34 -> 1383.11 | ... K36: =K33-K34 -> 1404.21
A40: Adjust profit | B40: NI + Current Year R&D exp- amortization of r and D
A41: Balance Sheet
A43: Year | B43: 2016 | C43: 2017 | D43: 2018 | E43: 2019 | F43: 2020 | G43: 2021 | H43: 2022 | I43: 2023 | J43: 2024 | K43: 2025 | L43: 2026 | M43: 2027 | N43: 2028 | O43: 2029 | P43: 2030
A44: SOURCES OF FUNDS : | O44: 2029 | P44: 2030
A45: Share Capital | B45: =Bal.sheet!B4 -> 175.91 | C45: =Bal.sheet!C4 -> 176.15 | D45: =Bal.sheet!D4 -> 176.15 | E45: =Bal.sheet!E4 -> 176.63 | F45: =Bal.sheet!F4 -> 176.71 | G45: =Bal.sheet!G4 -> 176.74 | H45: =Bal.sheet!H4 -> 176.79 | I45: =Bal.sheet!I4 -> 177.18 | ... K45: =Bal.sheet!K4 -> 177.23 | L45: 177.2 | M45: 177.2 | N45: 177.2 | O45: 177.2 | P45: 177.2
A46: Reserves Total | B46: =Bal.sheet!B5 -> 2918.38 | C46: =Bal.sheet!C5 -> 3481.73 | D46: =Bal.sheet!D5 -> 4050.71 | E46: =Bal.sheet!E5 -> 3792.19 | F46: =Bal.sheet!F5 -> 4397.52 | G46: =Bal.sheet!G5 -> 5214.48 | H46: =Bal.sheet!H5 -> 5687.08 | I46: =Bal.sheet!I5 -> 6109.7 | ... K46: =Bal.sheet!K5 -> 7246.06 | L46: =(K46)*(1+$P$49) -> 17170774 | M46: =(L46)*(1+$P$49) -> 4.0689077e+10 | N46: =(M46)*(1+$P$49) -> 9.6419705e+13 | O46: =(N46)*(1+$P$49) -> 2.2848293e+17 | P46: =(O46)*(1+$P$49) -> 5.4142925e+20
A47: Total Shareholders Funds | B47: =Bal.sheet!B8 -> 3094.29 | C47: =Bal.sheet!C8 -> 3657.88 | D47: =Bal.sheet!D8 -> 4226.86 | E47: =Bal.sheet!E8 -> 3968.82 | F47: =Bal.sheet!F8 -> 4574.23 | G47: =Bal.sheet!G8 -> 5391.22 | H47: =Bal.sheet!H8 -> 5863.87 | I47: =Bal.sheet!I8 -> 6286.88 | ... K47: =Bal.sheet!K8 -> 7423.29 | L47: =L46+L45 -> 17170952 | M47: =M46+M45 -> 4.0689078e+10 | N47: =N46+N45 -> 9.6419705e+13 | O47: =O46+O45 -> 2.2848293e+17 | P47: =P46+P45 -> 5.4142925e+20
A48: Unsecured Loans | B48: =Bal.sheet!B10 -> 79.55 | C48: =Bal.sheet!C10 -> 74.68 | D48: =Bal.sheet!D10 -> 78.01 | E48: =Bal.sheet!E10 -> 82.13 | F48: =Bal.sheet!F10 -> 49.46 | G48: =Bal.sheet!G10 -> 152.93 | H48: =Bal.sheet!H10 -> 560.18 | I48: =Bal.sheet!I10 -> 437.7 | ... K48: =Bal.sheet!K10 -> 378.62 | L48: =K48*(1+$P$50) -> 546.31212 | M48: =L48*(1+$P$50) -> 788.27565 | N48: =M48*(1+$P$50) -> 1137.4057 | O48: =N48*(1+$P$50) -> 1641.1666 | P48: =O48*(1+$P$50) -> 2368.045
A49: Total Debt | B49: =Bal.sheet!B11 -> 87.23 | C49: =Bal.sheet!C11 -> 283.75 | D49: =Bal.sheet!D11 -> 286.61 | E49: =Bal.sheet!E11 -> 309.86 | F49: =Bal.sheet!F11 -> 150.65 | G49: =Bal.sheet!G11 -> 179.87 | H49: =Bal.sheet!H11 -> 560.18 | I49: =Bal.sheet!I11 -> 615.46 | ... K49: =Bal.sheet!K11 -> 378.72 | L49: =(K49)*(1+$P$50) -> 546.45641 | M49: =(L49)*(1+$P$50) -> 788.48385 | N49: =(M49)*(1+$P$50) -> 1137.7061 | O49: =(N49)*(1+$P$50) -> 1641.6001 | P49: =(O49)*(1+$P$50) -> 2368.6705
A50: YOY | C50: =(C49-B49)/B49 -> 2.2528946 | D50: =(D49-C49)/C49 -> 0.010079295 | E50: =(E49-D49)/D49 -> 0.081120687 | F50: =(F49-E49)/E49 -> -0.51381269 | G50: =(G49-F49)/F49 -> 0.19395951 | H50: =(H49-G49)/G49 -> 2.1143604 | I50: =(I49-H49)/H49 -> 0.098682566 | J50: =(J49-I49)/I49 -> 0.26078055 | K50: =(K49-J49)/J49 -> -0.5119336 | P50: =AVERAGE(B50:K50) -> 0.44290348
A51: Other Liabilities | B51: =Bal.sheet!B12 -> 49.99 | C51: =Bal.sheet!C12 -> 51.23 | D51: =Bal.sheet!D12 -> 54.29 | E51: =Bal.sheet!E12 -> 57.32 | F51: =Bal.sheet!F12 -> 59.35 | G51: =Bal.sheet!G12 -> 56.92 | H51: =Bal.sheet!H12 -> 60.82 | I51: =Bal.sheet!I12 -> 62.62 | ... K51: =Bal.sheet!K12 -> 64.49
A52: Total Liabilities | B52: =Bal.sheet!B13 -> 3231.51 | C52: =Bal.sheet!C13 -> 3992.86 | D52: =Bal.sheet!D13 -> 4567.76 | E52: =Bal.sheet!E13 -> 4336 | F52: =Bal.sheet!F13 -> 4784.23 | G52: =Bal.sheet!G13 -> 5628.01 | H52: =Bal.sheet!H13 -> 6484.87 | I52: =Bal.sheet!I13 -> 6964.96 | ... K52: =Bal.sheet!K13 -> 7866.5 | L52: =(K52)*(1+(K52-J52)/K52) -> 7976.04 | M52: =(L52)*(1+(L52-K52)/L52) -> 8085.58 | N52: =(M52)*(1+(M52-L52)/M52) -> 8195.12 | O52: =(N52)*(1+(N52-M52)/N52) -> 8304.66 | P52: =(O52)*(1+(O52-N52)/O52) -> 8414.2
A53: APPLICATION OF FUNDS :
A54: Gross Block | B54: =Bal.sheet!B15 -> 1131.34 | C54: =Bal.sheet!C15 -> 1549.58 | D54: =Bal.sheet!D15 -> 1671.38 | E54: =Bal.sheet!E15 -> 1774.43 | F54: =Bal.sheet!F15 -> 1982.29 | G54: =Bal.sheet!G15 -> 2168.03 | H54: =Bal.sheet!H15 -> 2501.1 | I54: =Bal.sheet!I15 -> 2937.65 | ... K54: =Bal.sheet!K15 -> 3722.26
A55: Less : Accumulated Depreciation | B55: =Bal.sheet!B16 -> 492.53 | C55: =Bal.sheet!C16 -> 556.25 | D55: =Bal.sheet!D16 -> 640.9 | E55: =Bal.sheet!E16 -> 737.81 | F55: =Bal.sheet!F16 -> 848.01 | G55: =Bal.sheet!G16 -> 963.22 | H55: =Bal.sheet!H16 -> 1102.1 | I55: =Bal.sheet!I16 -> 1275.68 | ... K55: =Bal.sheet!K16 -> 1686.64
A56: Net Block | B56: =Bal.sheet!B18 -> 638.81 | C56: =Bal.sheet!C18 -> 993.33 | D56: =Bal.sheet!D18 -> 1030.48 | E56: =Bal.sheet!E18 -> 1036.62 | F56: =Bal.sheet!F18 -> 1134.28 | G56: =Bal.sheet!G18 -> 1204.81 | H56: =Bal.sheet!H18 -> 1399 | I56: =Bal.sheet!I18 -> 1661.97 | ... K56: =Bal.sheet!K18 -> 2035.62
A57: YOY | C57: =(C56-B56)/B56 -> 0.5549694 | D57: =(D56-C56)/C56 -> 0.037399454 | E57: =(E56-D56)/D56 -> 0.0059583883 | F57: =(F56-E56)/E56 -> 0.094210029 | G57: =(G56-F56)/F56 -> 0.062180414 | H57: =(H56-G56)/G56 -> 0.16117894 | I57: =(I56-H56)/H56 -> 0.18796998 | J57: =(J56-I56)/I56 -> 0.13010463 | K57: =(K56-J56)/J56 -> 0.08381429 | P57: =AVERAGE(C57:K57) -> 0.14642061
A58: Capital Work in Progress | B58: =Bal.sheet!B21 -> 24.96 | C58: =Bal.sheet!C21 -> 28.25 | D58: =Bal.sheet!D21 -> 26.82 | E58: =Bal.sheet!E21 -> 21.69 | F58: =Bal.sheet!F21 -> 105.83 | G58: =Bal.sheet!G21 -> 107.26 | H58: =Bal.sheet!H21 -> 128.48 | I58: =Bal.sheet!I21 -> 109.43 | ... K58: =Bal.sheet!K21 -> 136.88 | L58: =(K58)*(1+$P$62) -> 149.50256 | M58: =(L58)*(1+$P$62) -> 163.28912 | N58: =(M58)*(1+$P$62) -> 178.34703 | O58: =(N58)*(1+$P$62) -> 194.79352 | P58: =(O58)*(1+$P$62) -> 212.75665
A59: Investments | B59: =Bal.sheet!B23 -> 2570.31 | C59: =Bal.sheet!C23 -> 3054.15 | D59: =Bal.sheet!D23 -> 3433.06 | E59: =Bal.sheet!E23 -> 2962.14 | F59: =Bal.sheet!F23 -> 2466.83 | G59: =Bal.sheet!G23 -> 3573.9 | H59: =Bal.sheet!H23 -> 5007.08 | I59: =Bal.sheet!I23 -> 5475.05 | ... K59: =Bal.sheet!K23 -> 6358.82 | L59: =(K59)*(1+$P$62) -> 6945.2064 | M59: =(L59)*(1+$P$62) -> 7585.6672 | N59: =(M59)*(1+$P$62) -> 8285.1889 | O59: =(N59)*(1+$P$62) -> 9049.2178 | P59: =(O59)*(1+$P$62) -> 9883.7026
A60: Current Assets, Loans & Advances | B60: =Bal.sheet!B24 -> 0 | C60: =Bal.sheet!C24 -> 0 | D60: =Bal.sheet!D24 -> 0 | E60: =Bal.sheet!E24 -> 0 | F60: =Bal.sheet!F24 -> 0 | G60: =Bal.sheet!G24 -> 0 | H60: =Bal.sheet!H24 -> 0 | I60: =Bal.sheet!I24 -> 0 | ... K60: =Bal.sheet!K24 -> 0
A61: Inventories | B61: =Bal.sheet!B25 -> 615.56 | C61: =Bal.sheet!C25 -> 599.27 | D61: =Bal.sheet!D25 -> 704.79 | E61: =Bal.sheet!E25 -> 732.9 | F61: =Bal.sheet!F25 -> 809.14 | G61: =Bal.sheet!G25 -> 1114.16 | H61: =Bal.sheet!H25 -> 1237.96 | I61: =Bal.sheet!I25 -> 1223.77 | ... K61: =Bal.sheet!K25 -> 1288.07 | L61: =(K61)*(1+$P$62) -> 1406.851 | M61: =(L61)*(1+$P$62) -> 1536.5855 | N61: =(M61)*(1+$P$62) -> 1678.2836 | O61: =(N61)*(1+$P$62) -> 1833.0486 | P61: =(O61)*(1+$P$62) -> 2002.0854
A62: YOY | C62: =(C61-B61)/B61 -> -0.026463708 | D62: =(D61-C61)/C61 -> 0.1760809 | E62: =(E61-D61)/D61 -> 0.039884221 | F62: =(F61-E61)/E61 -> 0.10402511 | G62: =(G61-F61)/F61 -> 0.37696814 | H62: =(H61-G61)/G61 -> 0.1111151 | I62: =(I61-H61)/H61 -> -0.011462406 | J62: =(J61-I61)/I61 -> -0.060378993 | K62: =(K61-J61)/J61 -> 0.12017776 | P62: =AVERAGE(C62:K62) -> 0.092216235
A63: Sundry Debtors | B63: =Bal.sheet!B26 -> 420.69 | C63: =Bal.sheet!C26 -> 333.25 | D63: =Bal.sheet!D26 -> 321.34 | E63: =Bal.sheet!E26 -> 431.46 | F63: =Bal.sheet!F26 -> 379.63 | G63: =Bal.sheet!G26 -> 281.24 | H63: =Bal.sheet!H26 -> 454.55 | I63: =Bal.sheet!I26 -> 561.18 | ... K63: =Bal.sheet!K26 -> 600.58 | L63: =(K63)*(1+$P$67) -> 655.03371 | M63: =(L63)*(1+$P$67) -> 714.42467 | N63: =(M63)*(1+$P$67) -> 779.20051 | O63: =(N63)*(1+$P$67) -> 849.84948 | P63: =(O63)*(1+$P$67) -> 926.9041
A64: Cash and Bank | B64: =Bal.sheet!B27 -> 55.63 | C64: =Bal.sheet!C27 -> 26.16 | D64: =Bal.sheet!D27 -> 87.02 | E64: =Bal.sheet!E27 -> 124.71 | F64: =Bal.sheet!F27 -> 525.6 | G64: =Bal.sheet!G27 -> 834.74 | H64: =Bal.sheet!H27 -> 136.18 | I64: =Bal.sheet!I27 -> 33.4 | ... K64: =Bal.sheet!K27 -> 133.02 | L64: =(K64)*(1+$P$67) -> 145.08073 | M64: =(L64)*(1+$P$67) -> 158.23499 | N64: =(M64)*(1+$P$67) -> 172.58192 | O64: =(N64)*(1+$P$67) -> 188.22968 | P64: =(O64)*(1+$P$67) -> 205.29619
A65: Loans and Advances | B65: =Bal.sheet!B28 -> 68.26 | C65: =Bal.sheet!C28 -> 91.81 | D65: =Bal.sheet!D28 -> 132.3 | E65: =Bal.sheet!E28 -> 109.88 | F65: =Bal.sheet!F28 -> 168.15 | G65: =Bal.sheet!G28 -> 148.71 | H65: =Bal.sheet!H28 -> 126.06 | I65: =Bal.sheet!I28 -> 140.4 | ... K65: =Bal.sheet!K28 -> 280.07 | L65: =(K65)*(1+$P$67) -> 305.46354 | M65: =(L65)*(1+$P$67) -> 333.15947 | N65: =(M65)*(1+$P$67) -> 363.36656 | O65: =(N65)*(1+$P$67) -> 396.31247 | P65: =(O65)*(1+$P$67) -> 432.24555
A66: Total Current Assets | B66: =Bal.sheet!B29 -> 1160.14 | C66: =Bal.sheet!C29 -> 1050.49 | D66: =Bal.sheet!D29 -> 1245.45 | E66: =Bal.sheet!E29 -> 1398.95 | F66: =Bal.sheet!F29 -> 1882.52 | G66: =Bal.sheet!G29 -> 2378.85 | H66: =Bal.sheet!H29 -> 1954.75 | I66: =Bal.sheet!I29 -> 1958.75 | ... K66: =Bal.sheet!K29 -> 2301.74 | L66: =(K66)*(1+$P$67) -> 2510.4354 | M66: =(L66)*(1+$P$67) -> 2738.0529 | N66: =(M66)*(1+$P$67) -> 2986.3082 | O66: =(N66)*(1+$P$67) -> 3257.0724 | P66: =(O66)*(1+$P$67) -> 3552.3864
A67: YOY | C67: =(C66-B66)/B66 -> -0.094514455 | D67: =(D66-C66)/C66 -> 0.18558958 | E67: =(E66-D66)/D66 -> 0.12324862 | F67: =(F66-E66)/E66 -> 0.34566639 | G67: =(G66-F66)/F66 -> 0.26365191 | H67: =(H66-G66)/G66 -> -0.17827942 | I67: =(I66-H66)/H66 -> 0.0020462975 | J67: =(J66-I66)/I66 -> 0.10897256 | K67: =(K66-J66)/J66 -> 0.059635393 | P67: =AVERAGE(B67:K67) -> 0.090668543
A68: Less : Current Liabilities and Provisions | B68: =Bal.sheet!B30 -> 0 | C68: =Bal.sheet!C30 -> 0 | D68: =Bal.sheet!D30 -> 0 | E68: =Bal.sheet!E30 -> 0 | F68: =Bal.sheet!F30 -> 0 | G68: =Bal.sheet!G30 -> 0 | H68: =Bal.sheet!H30 -> 0 | I68: =Bal.sheet!I30 -> 0 | ... K68: =Bal.sheet!K30 -> 0
A69: Current Liabilities | B69: =Bal.sheet!B31 -> 1070.85 | C69: =Bal.sheet!C31 -> 1061.37 | D69: =Bal.sheet!D31 -> 1080.62 | E69: =Bal.sheet!E31 -> 1145.54 | F69: =Bal.sheet!F31 -> 1188.38 | G69: =Bal.sheet!G31 -> 1715.09 | H69: =Bal.sheet!H31 -> 1844.16 | I69: =Bal.sheet!I31 -> 2108.21 | ... K69: =Bal.sheet!K31 -> 2663.03 | L69: =(K69)*(1+$P$72) -> 2986.0755 | M69: =(L69)*(1+$P$72) -> 3348.3087 | N69: =(M69)*(1+$P$72) -> 3754.4836 | O69: =(N69)*(1+$P$72) -> 4209.9306 | P69: =(O69)*(1+$P$72) -> 4720.6266
A70: Provisions | B70: =Bal.sheet!B32 -> 50.85 | C70: =Bal.sheet!C32 -> 64.51 | D70: =Bal.sheet!D32 -> 68.29 | E70: =Bal.sheet!E32 -> 88.92 | F70: =Bal.sheet!F32 -> 127.5 | G70: =Bal.sheet!G32 -> 161.06 | H70: =Bal.sheet!H32 -> 192.93 | I70: =Bal.sheet!I32 -> 202.51 | ... K70: =Bal.sheet!K32 -> 342.69 | L70: =(K70)*(1+$P$72) -> 384.26086 | M70: =(L70)*(1+$P$72) -> 430.87458 | N70: =(M70)*(1+$P$72) -> 483.14289 | O70: =(N70)*(1+$P$72) -> 541.75173 | P70: =(O70)*(1+$P$72) -> 607.47027
A71: Total Current Liabilities | B71: =Bal.sheet!B33 -> 1121.7 | C71: =Bal.sheet!C33 -> 1125.88 | D71: =Bal.sheet!D33 -> 1148.91 | E71: =Bal.sheet!E33 -> 1234.46 | F71: =Bal.sheet!F33 -> 1315.88 | G71: =Bal.sheet!G33 -> 1876.15 | H71: =Bal.sheet!H33 -> 2037.09 | I71: =Bal.sheet!I33 -> 2310.72 | ... K71: =Bal.sheet!K33 -> 3005.72 | L71: =(K71)*(1+$P$72) -> 3370.3363 | M71: =(L71)*(1+$P$72) -> 3779.1833 | N71: =(M71)*(1+$P$72) -> 4237.6265 | O71: =(N71)*(1+$P$72) -> 4751.6823 | P71: =(O71)*(1+$P$72) -> 5328.0969
A72: YOY | C72: =(C71-B71)/B71 -> 0.0037264866 | D72: =(D71-C71)/C71 -> 0.020455111 | E72: =(E71-D71)/D71 -> 0.074461881 | F72: =(F71-E71)/E71 -> 0.065955965 | G72: =(G71-F71)/F71 -> 0.42577591 | H72: =(H71-G71)/G71 -> 0.085782054 | I72: =(I71-H71)/H71 -> 0.13432396 | J72: =(J71-I71)/I71 -> 0.1577993 | K72: =(K71-J71)/J71 -> 0.12348665 | P72: =AVERAGE(B72:K72) -> 0.12130748
A73: Net Current Assets | B73: =Bal.sheet!B34 -> 38.44 | C73: =Bal.sheet!C34 -> -75.39 | D73: =Bal.sheet!D34 -> 96.54 | E73: =Bal.sheet!E34 -> 164.49 | F73: =Bal.sheet!F34 -> 566.64 | G73: =Bal.sheet!G34 -> 502.7 | H73: =Bal.sheet!H34 -> -82.34 | I73: =Bal.sheet!I34 -> -351.97 | ... K73: =Bal.sheet!K34 -> -703.98 | L73: =(K73)*(1+$P$79) -> -779.28254 | M73: =(L73)*(1+$P$79) -> -862.63995 | N73: =(M73)*(1+$P$79) -> -954.91385 | O73: =(N73)*(1+$P$79) -> -1057.058 | P73: =(O73)*(1+$P$79) -> -1170.1282
A74: Deferred Tax Assets | B74: =Bal.sheet!B36 -> 13.22 | C74: =Bal.sheet!C36 -> 5.79 | D74: =Bal.sheet!D36 -> 17.8 | E74: =Bal.sheet!E36 -> 102.61 | F74: =Bal.sheet!F36 -> 151.29 | G74: =Bal.sheet!G36 -> 148.95 | H74: =Bal.sheet!H36 -> 78.32 | I74: =Bal.sheet!I36 -> 100.24 | ... K74: =Bal.sheet!K36 -> 89.68 | L74: =(K74)*(1+$P$79) -> 99.272789 | M74: =(L74)*(1+$P$79) -> 109.89169 | N74: =(M74)*(1+$P$79) -> 121.64646 | O74: =(N74)*(1+$P$79) -> 134.6586 | P74: =(O74)*(1+$P$79) -> 149.06261
A75: Deferred Tax Liability | B75: =Bal.sheet!B37 -> 89.74 | C75: =Bal.sheet!C37 -> 104.07 | D75: =Bal.sheet!D37 -> 113.83 | E75: =Bal.sheet!E37 -> 110.93 | F75: =Bal.sheet!F37 -> 129.67 | G75: =Bal.sheet!G37 -> 131.5 | H75: =Bal.sheet!H37 -> 148.36 | I75: =Bal.sheet!I37 -> 177 | ... K75: =Bal.sheet!K37 -> 222.93 | L75: =(K75)*(1+$P$79) -> 246.77612 | M75: =(L75)*(1+$P$79) -> 273.17299 | N75: =(M75)*(1+$P$79) -> 302.39345 | O75: =(N75)*(1+$P$79) -> 334.73954 | P75: =(O75)*(1+$P$79) -> 370.54558
A76: Net Deferred Tax | B76: =Bal.sheet!B38 -> -76.52 | C76: =Bal.sheet!C38 -> -98.28 | D76: =Bal.sheet!D38 -> -96.03 | E76: =Bal.sheet!E38 -> -8.32 | F76: =Bal.sheet!F38 -> 21.62 | G76: =Bal.sheet!G38 -> 17.45 | H76: =Bal.sheet!H38 -> -70.04 | I76: =Bal.sheet!I38 -> -76.76 | ... K76: =Bal.sheet!K38 -> -133.25 | L76: =(K76)*(1+$P$79) -> -147.50334 | M76: =(L76)*(1+$P$79) -> -163.28131 | N76: =(M76)*(1+$P$79) -> -180.747 | O76: =(N76)*(1+$P$79) -> -200.08094 | P76: =(O76)*(1+$P$79) -> -221.48297
A77: Other Assets | B77: =Bal.sheet!B39 -> 35.51 | C77: =Bal.sheet!C39 -> 90.8 | D77: =Bal.sheet!D39 -> 76.89 | E77: =Bal.sheet!E39 -> 159.38 | F77: =Bal.sheet!F39 -> 489.03 | G77: =Bal.sheet!G39 -> 221.89 | H77: =Bal.sheet!H39 -> 102.69 | I77: =Bal.sheet!I39 -> 147.24 | ... K77: =Bal.sheet!K39 -> 172.41 | L77: =(K77)*(1+$P$79) -> 190.85216 | M77: =(L77)*(1+$P$79) -> 211.26702 | N77: =(M77)*(1+$P$79) -> 233.86559 | O77: =(N77)*(1+$P$79) -> 258.88146 | P77: =(O77)*(1+$P$79) -> 286.5732
A78: Total Assets | B78: =Bal.sheet!B43 -> 3231.51 | C78: =Bal.sheet!C43 -> 3992.86 | D78: =Bal.sheet!D43 -> 4567.76 | E78: =Bal.sheet!E43 -> 4336 | F78: =Bal.sheet!F43 -> 4784.23 | G78: =Bal.sheet!G43 -> 5628.01 | H78: =Bal.sheet!H43 -> 6484.87 | I78: =Bal.sheet!I43 -> 6964.96 | ... K78: =Bal.sheet!K43 -> 7866.5 | L78: =(K78)*(1+(K78-J78)/K78) -> 7976.04 | M78: =(L78)*(1+(L78-K78)/L78) -> 8085.58 | N78: =(M78)*(1+(M78-L78)/M78) -> 8195.12 | O78: =(N78)*(1+(N78-M78)/N78) -> 8304.66 | P78: =(O78)*(1+(O78-N78)/O78) -> 8414.2
A79: YOY | C79: =(C78-B78)/B78 -> 0.23560193 | D79: =(D78-C78)/C78 -> 0.14398201 | E79: =(E78-D78)/D78 -> -0.050738217 | F79: =(F78-E78)/E78 -> 0.10337408 | G79: =(G78-F78)/F78 -> 0.17636694 | H79: =(H78-G78)/G78 -> 0.1522492 | I79: =(I78-H78)/H78 -> 0.074032324 | J79: =(J78-I78)/I78 -> 0.11371207 | K79: =(K78-J78)/J78 -> 0.014121512 | P79: =AVERAGE(B79:K79) -> 0.10696687
A80: Contingent Liabilities | B80: =Bal.sheet!B44 -> 1183.31 | C80: =Bal.sheet!C44 -> 1055.31 | D80: =Bal.sheet!D44 -> 846.63 | E80: =Bal.sheet!E44 -> 536.74 | F80: =Bal.sheet!F44 -> 222.88 | G80: =Bal.sheet!G44 -> 241.7 | H80: =Bal.sheet!H44 -> 253.92 | I80: =Bal.sheet!I44 -> 248.38 | ... K80: =Bal.sheet!K44 -> 562.3
A81: Average inventory | C81: =(C61+B61)/2 -> 607.415 | D81: =(D61+C61)/2 -> 652.03 | E81: =(E61+D61)/2 -> 718.845 | F81: =(F61+E61)/2 -> 771.02 | G81: =(G61+F61)/2 -> 961.65 | H81: =(H61+G61)/2 -> 1176.06 | I81: =(I61+H61)/2 -> 1230.865 | J81: =(J61+I61)/2 -> 1186.825 | K81: =(K61+J61)/2 -> 1218.975
A82: Average Trade Receivables | C82: =(C63+B63)/2 -> 376.97 | D82: =(D63+C63)/2 -> 327.295 | E82: =(E63+D63)/2 -> 376.4 | F82: =(F63+E63)/2 -> 405.545 | G82: =(G63+F63)/2 -> 330.435 | H82: =(H63+G63)/2 -> 367.895 | I82: =(I63+H63)/2 -> 507.865 | J82: =(J63+I63)/2 -> 640.195 | K82: =(K63+J63)/2 -> 659.895
A83: Average Trade Payables | C83: =(C69+B69)/2 -> 1066.11 | D83: =(D69+C69)/2 -> 1070.995 | E83: =(E69+D69)/2 -> 1113.08 | F83: =(F69+E69)/2 -> 1166.96 | G83: =(G69+F69)/2 -> 1451.735 | H83: =(H69+G69)/2 -> 1779.625 | I83: =(I69+H69)/2 -> 1976.185 | J83: =(J69+I69)/2 -> 2252.5 | K83: =(K69+J69)/2 -> 2529.91
A84: WORKING CAPITA | B84: =B66-B69 -> 89.29 | C84: =C66-C69 -> -10.88 | D84: =D66-D69 -> 164.83 | E84: =E66-E69 -> 253.41 | F84: =F66-F69 -> 694.14 | G84: =G66-G69 -> 663.76 | H84: =H66-H69 -> 110.59 | I84: =I66-I69 -> -149.46 | ... K84: =K66-K69 -> -361.29 | L84: =L69-L66 -> 475.64004 | M84: =M69-M66 -> 610.25581 | N84: =N69-N66 -> 768.17543 | O84: =O69-O66 -> 952.85816 | P84: =P69-P66 -> 1168.2402
A85: CHANGE IN WORKING CAPITAL | C85: =C84-B84 -> -100.17 | D85: =D84-C84 -> 175.71 | E85: =E84-D84 -> 88.58 | F85: =F84-E84 -> 440.73 | G85: =G84-F84 -> -30.38 | H85: =H84-G84 -> -553.17 | I85: =I84-H84 -> -260.05 | J85: =J84-I84 -> -75.13 | ... P85: =P84-O84 -> 215.38206
A89: total lib- total Assets(balanced) | B89: 2016 | C89: 2017 | D89: 2018 | E89: 2019 | F89: 2020 | G89: 2021 | H89: 2022 | I89: 2023 | J89: 2024 | K89: 2025 | L89: 2026 | M89: 2027 | N89: 2028 | O89: 2029 | P89: 2030
B90: =B52-B78 -> 0 | C90: =C52-C78 -> 0 | D90: =D52-D78 -> 0 | E90: =E52-E78 -> 0 | F90: =F52-F78 -> 0 | G90: =G52-G78 -> 0 | H90: =H52-H78 -> 0 | I90: =I52-I78 -> 0 | ... P90: =P52-P78 -> 0
A92: Cash Flow from Fianncial Statement sheet
A95: INR in Cr. | B95: 2016 | C95: 2017 | D95: 2018 | E95: 2019 | F95: 2020 | G95: 2021 | H95: 2022 | I95: 2023 | J95: 2024 | K95: 2025 | L95: 2026 | M95: 2027 | N95: 2028 | O95: 2029 | P95: 2030
A96: Profit before tax | B96: 1209.35 | C96: 1294.35 | D96: 1373.13 | E96: 1503.35 | F96: 1408.47 | G96: 1683.31 | H96: 1896.31 | I96: 1828.67 | J96: 1966.7 | K96: 1808.34 | L96: 1887.55 | M96: 1967.7081 | N96: 2048.3321 | O96: 2128.832 | P96: 2208.4911
A97: Add: Depreciation | B97: 72.83 | C97: 75.43 | D97: 102.5 | E97: 108.83 | F97: 129.93 | G97: 143.4 | H97: 160.39 | I97: 188.29 | J97: 208.86 | K97: 250.93 | L97: 288.7643 | M97: 332.30313 | N97: 382.40657 | O97: 440.06443 | P97: 506.41573
A98: Add: Finance Cost | B98: 10.26 | C98: 16.23 | D98: 21.89 | E98: 29.8 | F98: 19.27 | G98: 9.14 | H98: 18.67 | I98: 46.37 | J98: 81.14 | K98: 99.58 | L98: 142.91224 | M98: 205.1005 | N98: 294.34999 | O98: 422.43639 | P98: 606.2596
A99: Cash Flow before Working Capital Changes | B99: 1292.44 | C99: 1386.01 | D99: 1497.52 | E99: 1641.98 | F99: 1557.67 | G99: 1835.85 | H99: 2075.37 | I99: 2063.33 | J99: 2256.7 | K99: 2158.85 | L99: 2319.2266 | M99: 2505.1117 | N99: 2725.0887 | O99: 2991.3329 | P99: 3321.1664
A100: Changes in working capital
A101: Inventories | B101: -64.95 | C101: 16.28 | D101: -105.52 | E101: -28.1 | F101: -76.24 | G101: -305.02 | H101: -123.8 | I101: 14.19 | J101: 73.89 | K101: -138.19 | L101: 836.93004 | M101: 134.61577 | N101: 157.91962 | O101: 184.68273 | P101: 215.38206
A102: Trade Receivable | B102: -78.59 | C102: 87.43 | D102: 10.82 | E102: -112.39 | F102: 53.94 | G102: 94.27 | H102: -176 | I102: -113.54 | J102: -158.17 | K102: 115.22
A103: Other current assets | B103: 0 | C103: -24.96 | D103: -90.17 | E103: 67.91 | F103: -52.16 | G103: 96.39 | H103: 34.37 | I103: 42.95 | J103: -66.58 | K103: -87.93
A104: Trade payable | B104: 204.25 | C104: -24.18 | D104: 31.57 | E104: 37.75 | F104: 33.4 | G104: 448.92 | H104: 100.66 | I104: 237.83 | J104: 240.2 | K104: 282.45
A105: Other current liabilities
A106: Net Changes in working capital | B106: 60.71 | C106: 54.57 | D106: -153.3 | E106: -34.83 | F106: -41.06 | G106: 334.56 | H106: -164.77 | I106: 181.43 | J106: 89.34 | K106: 171.55
A107: Tax paid | B107: -260.73 | C107: -274.5 | D107: -301.07 | E107: -319.56 | F107: -268.94 | G107: -274.6 | H107: -328.45 | I107: -432.35 | J107: -390.33 | K107: -327.67 | L107: 0 | M107: 0 | N107: 0 | O107: 0 | P107: 0
A108: Net cash flow from opreating | B108: 960.3 | C108: 926.94 | D108: 816.41 | E108: 1123.57 | F108: 1154.77 | G108: 1704.17 | H108: 1319.95 | I108: 1561.91 | J108: 1653.33 | K108: 1622.97 | L108: 3156.1566 | M108: 2639.7275 | N108: 2883.0083 | O108: 3176.0156 | P108: 3536.5485
A110: Capex | B110: -106.84 | C110: -411.12 | D110: -110.74 | E110: -125.28 | F110: -264.54 | G110: -249.9 | H110: -296.77 | I110: -410.05 | J110: -456.55 | K110: -351.78
A111: Net cash flow from investing acticituies | B111: -494.33 | C111: -678.94 | D111: -261.18 | E111: 417.78 | F111: -330.28 | G111: -1120.37 | H111: -681.7 | I111: -617.2 | J111: -736.09 | K111: -98.9
A113: Finace cost | B113: 10.26 | C113: 16.23 | D113: 21.89 | E113: 29.8 | F113: 19.27 | G113: 9.14 | H113: 18.67 | I113: 46.37 | J113: 81.14 | K113: 99.58 | L113: 142.91224 | M113: 205.1005 | N113: 294.34999 | O113: 422.43639 | P113: 606.2596
...

Sheet financial satement
A1: FINANCIAL STATEMENTS OF TATA STEEL LTD | B1: ACTUAL PERIOD | G1: FORECASTED PERIOD
A2: Number of Days | B2: 365 | C2: 365 | D2: 365 | E2: 365 | F2: 365 | G2: 365 | H2: 365 | I2: 365 | J2: 365 | K2: 365
A4: Profit and Loss Statement
A5: Particulars | B5: 2016 | C5: 2017 | D5: 2018 | E5: 2019 | F5: 2020 | G5: 2021 | H5: 2022 | I5: 2023 | J5: 2024 | K5: 2025 | L5: 2026 | M5: 2027 | N5: 2028 | O5: 2029 | P5: 2030
A7: Revenue from Operations | B7: =PL!K4 -> 5422.57 | C7: =PL!J4 -> 5369.84 | D7: =PL!I4 -> 5609.06 | E7: =PL!H4 -> 6273.19 | F7: =PL!G4 -> 6309.8 | G7: =PL!F4 -> 7184.73 | H7: =PL!E4 -> 8179.5 | I7: =PL!D4 -> 8684.35 | J7: =PL!C4 -> 9135.6 | K7: =PL!B4 -> 9070.71 | L7: =Assumption!L5 -> 9609.8811 | M7: =Assumption!M5 -> 10181.101 | N7: =Assumption!N5 -> 10786.275 | O7: =Assumption!O5 -> 11427.421 | P7: =Assumption!P5 -> 12106.677
A8: Other revenues | B8: =PL!K6 -> 194.36 | C8: =PL!J6 -> 274.64 | D8: =PL!I6 -> 283.23 | E8: =PL!H6 -> 274.74 | F8: =PL!G6 -> 276.9 | G8: =PL!F6 -> 276.65 | H8: =PL!E6 -> 341.55 | I8: =PL!D6 -> 392.17 | J8: =PL!C6 -> 417.62 | K8: =PL!B6 -> 451.94
A9: Revenue | B9: =PL!K8 -> 5558.17 | C9: =PL!J8 -> 5573.48 | D9: =PL!I8 -> 5949.55 | E9: =PL!H8 -> 6537.84 | F9: =PL!G8 -> 6656.59 | G9: =PL!F8 -> 7638.09 | H9: =PL!E8 -> 8549.54 | I9: =PL!D8 -> 9101.5 | J9: =PL!C8 -> 9504.04 | K9: =PL!B8 -> 9509.75 | L9: =Assumption!L8 -> 9596.2143 | M9: =Assumption!M8 -> 10166.622 | N9: =Assumption!N8 -> 10770.935 | O9: =Assumption!O8 -> 11411.169 | P9: =Assumption!P8 -> 12089.459
A11: Cost of Material Consumed | B11: =PL!K10 -> 2150.59 | C11: =PL!J10 -> 2129.17 | D11: =PL!I10 -> 2281.22 | E11: =PL!H10 -> 2511.23 | F11: =PL!G10 -> 2531.18 | G11: =PL!F10 -> 3065.28 | H11: =PL!E10 -> 3444.55 | I11: =PL!D10 -> 3797.74 | J11: =PL!C10 -> 3797.27 | K11: =PL!B10 -> 3896.24 | L11: =Assumption!L10 -> 4154.89 | M11: =Assumption!M10 -> 4430.7104 | N11: =Assumption!N10 -> 4724.8409 | O11: =Assumption!O10 -> 5038.4972 | P11: =Assumption!P10 -> 5372.9754
A12: Purchase Of Stock-In Trade | B12: =PL!K7 -> 23.77 | C12: =PL!J7 -> 8.19 | D12: =PL!I7 -> 74.03 | E12: =PL!H7 -> -10.09 | F12: =PL!G7 -> 69.89 | G12: =PL!F7 -> 176.71 | H12: =PL!E7 -> 28.49 | I12: =PL!D7 -> 24.98 | J12: =PL!C7 -> -49.18 | K12: =PL!B7 -> -12.9
A13: Changes In Inventories Of FG,WIP And Stock-In Trade | B13: =PL!K11 -> 47.77 | C13: =PL!J11 -> 50.61 | D13: =PL!I11 -> 59.43 | E13: =PL!H11 -> 63.99 | F13: =PL!G11 -> 66.48 | G13: =PL!F11 -> 70.72 | H13: =PL!E11 -> 85.02 | I13: =PL!D11 -> 93.32 | J13: =PL!C11 -> 99.23 | K13: =PL!B11 -> 97.85 | L13: =Assumption!L11 -> 104.34572 | M13: =Assumption!M11 -> 111.27267 | N13: =Assumption!N11 -> 118.65945 | O13: =Assumption!O11 -> 126.5366 | P13: =Assumption!P11 -> 134.93667
A14: Cost of Goods sold | B14: =B11+B12+B13 -> 2222.13 | C14: =C11+C12+C13 -> 2187.97 | D14: =D11+D12+D13 -> 2414.68 | E14: =E11+E12+E13 -> 2565.13 | F14: =F11+F12+F13 -> 2667.55 | G14: =G11+G12+G13 -> 3312.71 | H14: =H11+H12+H13 -> 3558.06 | I14: =I11+I12+I13 -> 3916.04 | ... P14: =P11+P12+P13 -> 5507.9121
A15: Gross Margin | B15: =B9-B14 -> 3336.04 | C15: =C9-C14 -> 3385.51 | D15: =D9-D14 -> 3534.87 | E15: =E9-E14 -> 3972.71 | F15: =F9-F14 -> 3989.04 | G15: =G9-G14 -> 4325.38 | H15: =H9-H14 -> 4991.48 | I15: =I9-I14 -> 5185.46 | ... P15: =P9-P14 -> 6581.5472
A17: Employee Benefit Expenses | B17: =PL!K12 -> 431.89 | C17: =PL!J12 -> 425.3 | D17: =PL!I12 -> 461.13 | E17: =PL!H12 -> 572.33 | F17: =PL!G12 -> 578.26 | G17: =PL!F12 -> 655.82 | H17: =PL!E12 -> 678.71 | I17: =PL!D12 -> 725.96 | J17: =PL!C12 -> 782.14 | K17: =PL!B12 -> 776.86 | L17: =Assumption!L12 -> 828.43147 | M17: =Assumption!M12 -> 883.4265 | N17: =Assumption!N12 -> 942.07234 | O17: =Assumption!O12 -> 1004.6114 | P17: =Assumption!P12 -> 1071.302
A18: Other Expenses | B18: =PL!K13+PL!K14+PL!K15 -> 1635.48 | C18: =PL!J13+PL!J14+PL!J15 -> 1582.39 | D18: =PL!I13+PL!I14+PL!I15 -> 1650.25 | E18: =PL!H13+PL!H14+PL!H15 -> 1748.31 | F18: =PL!G13+PL!G14+PL!G15 -> 1923 | G18: =PL!F13+PL!F14+PL!F15 -> 2010.42 | H18: =PL!E13+PL!E14+PL!E15 -> 2265.89 | I18: =PL!D13+PL!D14+PL!D15 -> 2421.15 | J18: =PL!C13+PL!C14+PL!C15 -> 2568.7 | K18: =PL!B13+PL!B14+PL!B15 -> 2579.95 | L18: =Assumption!L13+Assumption!L14 -> 2593.8737 | M18: =Assumption!M13+Assumption!M14 -> 2766.0667 | N18: =Assumption!N13+Assumption!N14 -> 2949.6907 | O18: =Assumption!O13+Assumption!O14 -> 3145.5045 | P18: =Assumption!P13+Assumption!P14 -> 3354.3173
A19: EBITDA | B19: =B15-B17-B18 -> 1268.67 | C19: =C15-C17-C18 -> 1377.82 | D19: =D15-D17-D18 -> 1423.49 | E19: =E15-E17-E18 -> 1652.07 | F19: =F15-F17-F18 -> 1487.78 | G19: =G15-G17-G18 -> 1659.14 | H19: =H15-H17-H18 -> 2046.88 | I19: =I15-I17-I18 -> 2038.35 | ... P19: =P15-P17-P18 -> 2155.9278
A21: Depreciation And Amortisation Expenses | B21: =PL!K21 -> 72.83 | C21: =PL!J21 -> 75.43 | D21: =PL!I21 -> 102.5 | E21: =PL!H21 -> 108.83 | F21: =PL!G21 -> 129.93 | G21: =PL!F21 -> 143.4 | H21: =PL!E21 -> 160.39 | I21: =PL!D21 -> 188.29 | J21: =PL!C21 -> 208.86 | K21: =PL!B21 -> 250.93 | L21: =Assumption!L23 -> 288.7643 | M21: =Assumption!M23 -> 332.30313 | N21: =Assumption!N23 -> 382.40657 | O21: =Assumption!O23 -> 440.06443 | P21: =Assumption!P23 -> 506.41573
A22: EBIT | B22: =B19-B21 -> 1195.84 | C22: =C19-C21 -> 1302.39 | D22: =D19-D21 -> 1320.99 | E22: =E19-E21 -> 1543.24 | F22: =F19-F21 -> 1357.85 | G22: =G19-G21 -> 1515.74 | H22: =H19-H21 -> 1886.49 | I22: =I19-I21 -> 1850.06 | ... P22: =P19-P21 -> 1649.5121
A24: Finance Cost | B24: =PL!K19 -> 10.26 | C24: =PL!J19 -> 16.23 | D24: =PL!I19 -> 21.89 | E24: =PL!H19 -> 29.8 | F24: =PL!G19 -> 19.27 | G24: =PL!F19 -> 9.14 | H24: =PL!E19 -> 18.67 | I24: =PL!D19 -> 46.37 | J24: =PL!C19 -> 81.14 | K24: =PL!B19 -> 99.58 | L24: =Assumption!L19 -> 142.91224 | M24: =Assumption!M19 -> 205.1005 | N24: =Assumption!N19 -> 294.34999 | O24: =Assumption!O19 -> 422.43639 | P24: =Assumption!P19 -> 606.2596
A25: EBT | B25: =B22-B24 -> 1185.58 | C25: =C22-C24 -> 1286.16 | D25: =D22-D24 -> 1299.1 | E25: =E22-E24 -> 1513.44 | F25: =F22-F24 -> 1338.58 | G25: =G22-G24 -> 1506.6 | H25: =H22-H24 -> 1867.82 | I25: =I22-I24 -> 1803.69 | ... P25: =P22-P24 -> 1043.2525
A26: Tax Rate | B26: =Assumption!B27 -> 0.21425559 | C26: =Assumption!C27 -> 0.2401437 | D26: =Assumption!D27 -> 0.2478498 | E26: =Assumption!E27 -> 0.24563807 | F26: =Assumption!F27 -> 0.30202986 | G26: =Assumption!G27 -> 0.17807178 | H26: =Assumption!H27 -> 0.19984602 | I26: =Assumption!I27 -> 0.23178594 | ... P26: =Assumption!P27 -> 0
A27: Current Tax | B27: =PL!K23 -> 259.11 | C27: =PL!J23 -> 310.83 | D27: =PL!I23 -> 340.33 | E27: =PL!H23 -> 369.28 | F27: =PL!G23 -> 425.4 | G27: =PL!F23 -> 299.75 | H27: =PL!E23 -> 378.97 | I27: =PL!D23 -> 423.86 | J27: =PL!C23 -> 443.8 | K27: =PL!B23 -> 393.12 | L27: =L25*L26 -> 0 | M27: =M25*M26 -> 0 | N27: =N25*N26 -> 0 | O27: =O25*O26 -> 0 | P27: =P25*P26 -> 0
A28: Deferred Tax | B28: =PL!K25 -> 12.98 | C28: =PL!J25 -> -14.81 | D28: =PL!I25 -> -39.25 | E28: =PL!H25 -> -130.22 | F28: =PL!G25 -> -187.28 | G28: =PL!F25 -> 1.67 | H28: =PL!E25 -> 84.41 | I28: =PL!D25 -> 31.55 | J28: =PL!C25 -> 13.69 | K28: =PL!B25 -> 12 | L28: =Assumption!L28 -> 77.980492 | M28: =Assumption!M28 -> 506.74643 | N28: =Assumption!N28 -> 3293.028 | O28: =Assumption!O28 -> 21399.329 | P28: =Assumption!P28 -> 139060.85
A29: Net Income | B29: =B25-B27-B28 -> 913.49 | C29: =C25-C27-C28 -> 990.14 | D29: =D25-D27-D28 -> 998.02 | E29: =E25-E27-E28 -> 1274.38 | F29: =F25-F27-F28 -> 1100.46 | G29: =G25-G27-G28 -> 1205.18 | H29: =H25-H27-H28 -> 1404.44 | I29: =I25-I27-I28 -> 1348.28 | ... P29: =P25-P27-P28 -> -138017.6
A30: EPS | B30: =PL!K38 -> 5.33 | C30: =PL!J38 -> 5.67 | D30: =PL!I38 -> 6.09 | E30: =PL!H38 -> 7.16 | F30: =PL!G38 -> 6.62 | G30: =PL!F38 -> 7.82 | H30: =PL!E38 -> 8.11 | I30: =PL!D38 -> 7.75 | J30: =PL!C38 -> 8.52 | K30: =PL!B38 -> 7.92
A31: Dividend | B31: =PL!K34 -> 423.2 | C31: =PL!J34 -> 220.19 | D31: =PL!I34 -> 220.19 | E31: =PL!H34 -> 220.79 | F31: =PL!G34 -> 247.39 | G31: =PL!F34 -> 309.3 | H31: =PL!E34 -> 0 | I31: =PL!D34 -> 0 | J31: =PL!C34 -> 0 | K31: =PL!B34 -> 0 | L31: =Assumption!L34 -> 0 | M31: =Assumption!M34 -> 0 | N31: =Assumption!N34 -> 0 | O31: =Assumption!O34 -> 0 | P31: =Assumption!P34 -> 0
A32: Rate of Dividend | B32: =PL!K36 -> 225 | C32: =PL!J36 -> 225 | D32: =PL!I36 -> 750 | E32: =PL!H36 -> 275 | F32: =PL!G36 -> 300 | G32: =PL!F36 -> 475 | H32: =PL!E36 -> 520 | I32: =PL!D36 -> 520 | J32: =PL!C36 -> 550 | K32: =PL!B36 -> 800
A35: Balance Sheet
A37: INR in Cr. | B37: 2016 | C37: 2017 | D37: 2018 | E37: 2019 | F37: 2020 | G37: 2021 | H37: 2022 | I37: 2023 | J37: 2024 | K37: 2025 | L37: 2026 | M37: 2027 | N37: 2028 | O37: 2029 | P37: 2030
A38: Share Capital | B38: =Bal.sheet!B4 -> 175.91 | C38: =Bal.sheet!C4 -> 176.15 | D38: =Bal.sheet!D4 -> 176.15 | E38: =Bal.sheet!E4 -> 176.63 | F38: =Bal.sheet!F4 -> 176.71 | G38: =Bal.sheet!G4 -> 176.74 | H38: =Bal.sheet!H4 -> 176.79 | I38: =Bal.sheet!I4 -> 177.18 | ... K38: =Bal.sheet!K4 -> 177.23 | L38: =Assumption!L45 -> 177.2 | M38: =Assumption!M45 -> 177.2 | N38: =Assumption!N45 -> 177.2 | O38: =Assumption!O45 -> 177.2 | P38: =Assumption!P45 -> 177.2
A39: Reserves | B39: =Bal.sheet!B5 -> 2918.38 | C39: =Bal.sheet!C5 -> 3481.73 | D39: =Bal.sheet!D5 -> 4050.71 | E39: =Bal.sheet!E5 -> 3792.19 | F39: =Bal.sheet!F5 -> 4397.52 | G39: =Bal.sheet!G5 -> 5214.48 | H39: =Bal.sheet!H5 -> 5687.08 | I39: =Bal.sheet!I5 -> 6109.7 | ... K39: =Bal.sheet!K5 -> 7246.06 | L39: =Assumption!L46 -> 17170774 | M39: =Assumption!M46 -> 4.0689077e+10 | N39: =Assumption!N46 -> 9.6419705e+13 | O39: =Assumption!O46 -> 2.2848293e+17 | P39: =Assumption!P46 -> 5.4142925e+20
A40: Employee Stock Options
A41: Total Equity | B41: =Bal.sheet!B8 -> 3094.29 | C41: =Bal.sheet!C8 -> 3657.88 | D41: =Bal.sheet!D8 -> 4226.86 | E41: =Bal.sheet!E8 -> 3968.82 | F41: =Bal.sheet!F8 -> 4574.23 | G41: =Bal.sheet!G8 -> 5391.22 | H41: =Bal.sheet!H8 -> 5863.87 | I41: =Bal.sheet!I8 -> 6286.88 | ... K41: =Bal.sheet!K8 -> 7423.29 | L41: =Assumption!L47 -> 17170952 | M41: =Assumption!M47 -> 4.0689078e+10 | N41: =Assumption!N47 -> 9.6419705e+13 | O41: =Assumption!O47 -> 2.2848293e+17 | P41: =Assumption!P47 -> 5.4142925e+20
A43: Long Term Borrowings | B43: =Bal.sheet!B10 -> 79.55 | C43: =Bal.sheet!C10 -> 74.68 | D43: =Bal.sheet!D10 -> 78.01 | E43: =Bal.sheet!E10 -> 82.13 | F43: =Bal.sheet!F10 -> 49.46 | G43: =Bal.sheet!G10 -> 152.93 | H43: =Bal.sheet!H10 -> 560.18 | I43: =Bal.sheet!I10 -> 437.7 | ... K43: =Bal.sheet!K10 -> 378.62 | L43: =Assumption!L48 -> 546.31212 | M43: =Assumption!M48 -> 788.27565 | N43: =Assumption!N48 -> 1137.4057 | O43: =Assumption!O48 -> 1641.1666 | P43: =Assumption!P48 -> 2368.045
A44: Deferred Tax Liabilities [Net] | B44: =Bal.sheet!B37 -> 89.74 | C44: =Bal.sheet!C37 -> 104.07 | D44: =Bal.sheet!D37 -> 113.83 | E44: =Bal.sheet!E37 -> 110.93 | F44: =Bal.sheet!F37 -> 129.67 | G44: =Bal.sheet!G37 -> 131.5 | H44: =Bal.sheet!H37 -> 148.36 | I44: =Bal.sheet!I37 -> 177 | ... K44: =Bal.sheet!K37 -> 222.93 | L44: =Assumption!L75 -> 246.77612 | M44: =Assumption!M75 -> 273.17299 | N44: =Assumption!N75 -> 302.39345 | O44: =Assumption!O75 -> 334.73954 | P44: =Assumption!P75 -> 370.54558
A45: Other Non-current Liabilities | B45: =Bal.sheet!B12 -> 49.99 | C45: =Bal.sheet!C12 -> 51.23 | D45: =Bal.sheet!D12 -> 54.29 | E45: =Bal.sheet!E12 -> 57.32 | F45: =Bal.sheet!F12 -> 59.35 | G45: =Bal.sheet!G12 -> 56.92 | H45: =Bal.sheet!H12 -> 60.82 | I45: =Bal.sheet!I12 -> 62.62 | ... K45: =Bal.sheet!K12 -> 64.49
A46: Long Term Provisions | B46: =Bal.sheet!B32 -> 50.85 | C46: =Bal.sheet!C32 -> 64.51 | D46: =Bal.sheet!D32 -> 68.29 | E46: =Bal.sheet!E32 -> 88.92 | F46: =Bal.sheet!F32 -> 127.5 | G46: =Bal.sheet!G32 -> 161.06 | H46: =Bal.sheet!H32 -> 192.93 | I46: =Bal.sheet!I32 -> 202.51 | ... K46: =Bal.sheet!K32 -> 342.69 | L46: =Assumption!L70 -> 384.26086 | M46: =Assumption!M70 -> 430.87458 | N46: =Assumption!N70 -> 483.14289 | O46: =Assumption!O70 -> 541.75173 | P46: =Assumption!P70 -> 607.47027
A47: Total Non-Current Liabilities | B47: =Bal.sheet!B11+Bal.sheet!B12 -> 137.22 | C47: =Bal.sheet!C11+Bal.sheet!C12 -> 334.98 | D47: =Bal.sheet!D11+Bal.sheet!D12 -> 340.9 | E47: =Bal.sheet!E11+Bal.sheet!E12 -> 367.18 | F47: =Bal.sheet!F11+Bal.sheet!F12 -> 210 | G47: =Bal.sheet!G11+Bal.sheet!G12 -> 236.79 | H47: =Bal.sheet!H11+Bal.sheet!H12 -> 621 | I47: =Bal.sheet!I11+Bal.sheet!I12 -> 678.08 | ... K47: =Bal.sheet!K11+Bal.sheet!K12 -> 443.21
A49: Short Term Borrowings | B49: =Bal.sheet!B9 -> 7.68 | C49: =Bal.sheet!C9 -> 209.07 | D49: =Bal.sheet!D9 -> 208.6 | E49: =Bal.sheet!E9 -> 227.73 | F49: =Bal.sheet!F9 -> 101.19 | G49: =Bal.sheet!G9 -> 26.94 | H49: =Bal.sheet!H9 -> 0 | I49: =Bal.sheet!I9 -> 177.76 | ... K49: =Bal.sheet!K9 -> 0.1
A50: Trade payable | B50: =Bal.sheet!B31 -> 1070.85 | C50: =Bal.sheet!C31 -> 1061.37 | D50: =Bal.sheet!D31 -> 1080.62 | E50: =Bal.sheet!E31 -> 1145.54 | F50: =Bal.sheet!F31 -> 1188.38 | G50: =Bal.sheet!G31 -> 1715.09 | H50: =Bal.sheet!H31 -> 1844.16 | I50: =Bal.sheet!I31 -> 2108.21 | ... K50: =Bal.sheet!K31 -> 2663.03 | L50: =Assumption!L69 -> 2986.0755 | M50: =Assumption!M69 -> 3348.3087 | N50: =Assumption!N69 -> 3754.4836 | O50: =Assumption!O69 -> 4209.9306 | P50: =Assumption!P69 -> 4720.6266
A51: Other short term financial liabilities | B51: =Bal.sheet!B28 -> 68.26 | C51: =Bal.sheet!C28 -> 91.81 | D51: =Bal.sheet!D28 -> 132.3 | E51: =Bal.sheet!E28 -> 109.88 | F51: =Bal.sheet!F28 -> 168.15 | G51: =Bal.sheet!G28 -> 148.71 | H51: =Bal.sheet!H28 -> 126.06 | I51: =Bal.sheet!I28 -> 140.4 | ... K51: =Bal.sheet!K28 -> 280.07 | L51: =Assumption!L65 -> 305.46354 | M51: =Assumption!M65 -> 333.15947 | N51: =Assumption!N65 -> 363.36656 | O51: =Assumption!O65 -> 396.31247 | P51: =Assumption!P65 -> 432.24555
A52: Other current liabilities
A53: Short Term Provisions | B53: =Bal.sheet!B32 -> 50.85 | C53: =Bal.sheet!C32 -> 64.51 | D53: =Bal.sheet!D32 -> 68.29 | E53: =Bal.sheet!E32 -> 88.92 | F53: =Bal.sheet!F32 -> 127.5 | G53: =Bal.sheet!G32 -> 161.06 | H53: =Bal.sheet!H32 -> 192.93 | I53: =Bal.sheet!I32 -> 202.51 | ... K53: =Bal.sheet!K32 -> 342.69
A54: Total Current Liabilities | B54: =Bal.sheet!B33 -> 1121.7 | C54: =Bal.sheet!C33 -> 1125.88 | D54: =Bal.sheet!D33 -> 1148.91 | E54: =Bal.sheet!E33 -> 1234.46 | F54: =Bal.sheet!F33 -> 1315.88 | G54: =Bal.sheet!G33 -> 1876.15 | H54: =Bal.sheet!H33 -> 2037.09 | I54: =Bal.sheet!I33 -> 2310.72 | ... K54: =Bal.sheet!K33 -> 3005.72 | L54: =Assumption!L71 -> 3370.3363 | M54: =Assumption!M71 -> 3779.1833 | N54: =Assumption!N71 -> 4237.6265 | O54: =Assumption!O71 -> 4751.6823 | P54: =Assumption!P71 -> 5328.0969
A56: Total Liabilities & Equity | B56: =Bal.sheet!B13 -> 3231.51 | C56: =Bal.sheet!C13 -> 3992.86 | D56: =Bal.sheet!D13 -> 4567.76 | E56: =Bal.sheet!E13 -> 4336 | F56: =Bal.sheet!F13 -> 4784.23 | G56: =Bal.sheet!G13 -> 5628.01 | H56: =Bal.sheet!H13 -> 6484.87 | I56: =Bal.sheet!I13 -> 6964.96 | ... K56: =Bal.sheet!K13 -> 7866.5 | L56: =Assumption!L52 -> 7976.04 | M56: =Assumption!M52 -> 8085.58 | N56: =Assumption!N52 -> 8195.12 | O56: =Assumption!O52 -> 8304.66 | P56: =Assumption!P52 -> 8414.2
A58: Propert, Plant & Equipment | B58: =Bal.sheet!B18 -> 638.81 | C58: =Bal.sheet!C18 -> 993.33 | D58: =Bal.sheet!D18 -> 1030.48 | E58: =Bal.sheet!E18 -> 1036.62 | F58: =Bal.sheet!F18 -> 1134.28 | G58: =Bal.sheet!G18 -> 1204.81 | H58: =Bal.sheet!H18 -> 1399 | I58: =Bal.sheet!I18 -> 1661.97 | ... K58: =Bal.sheet!K18 -> 2035.62 | L58: =Assumption!L56 -> 0 | M58: =Assumption!M56 -> 0 | N58: =Assumption!N56 -> 0 | O58: =Assumption!O56 -> 0 | P58: =Assumption!P56 -> 0
A59: Intangible Assets
A60: Capital Work-In-Progress | B60: =Bal.sheet!B21 -> 24.96 | C60: =Bal.sheet!C21 -> 28.25 | D60: =Bal.sheet!D21 -> 26.82 | E60: =Bal.sheet!E21 -> 21.69 | F60: =Bal.sheet!F21 -> 105.83 | G60: =Bal.sheet!G21 -> 107.26 | H60: =Bal.sheet!H21 -> 128.48 | I60: =Bal.sheet!I21 -> 109.43 | ... K60: =Bal.sheet!K21 -> 136.88 | L60: =Assumption!L58 -> 149.50256 | M60: =Assumption!M58 -> 163.28912 | N60: =Assumption!N58 -> 178.34703 | O60: =Assumption!O58 -> 194.79352 | P60: =Assumption!P58 -> 212.75665
A61: Non-Current Investments | B61: =Bal.sheet!B23 -> 2570.31 | C61: =Bal.sheet!C23 -> 3054.15 | D61: =Bal.sheet!D23 -> 3433.06 | E61: =Bal.sheet!E23 -> 2962.14 | F61: =Bal.sheet!F23 -> 2466.83 | G61: =Bal.sheet!G23 -> 3573.9 | H61: =Bal.sheet!H23 -> 5007.08 | I61: =Bal.sheet!I23 -> 5475.05 | ... K61: =Bal.sheet!K23 -> 6358.82 | L61: =Assumption!L59 -> 6945.2064 | M61: =Assumption!M59 -> 7585.6672 | N61: =Assumption!N59 -> 8285.1889 | O61: =Assumption!O59 -> 9049.2178 | P61: =Assumption!P59 -> 9883.7026
A62: Financial Assets | B62: =Bal.sheet!B39 -> 35.51 | C62: =Bal.sheet!C39 -> 90.8 | D62: =Bal.sheet!D39 -> 76.89 | E62: =Bal.sheet!E39 -> 159.38 | F62: =Bal.sheet!F39 -> 489.03 | G62: =Bal.sheet!G39 -> 221.89 | H62: =Bal.sheet!H39 -> 102.69 | I62: =Bal.sheet!I39 -> 147.24 | ... K62: =Bal.sheet!K39 -> 172.41 | L62: =Assumption!L77 -> 190.85216 | M62: =Assumption!M77 -> 211.26702 | N62: =Assumption!N77 -> 233.86559 | O62: =Assumption!O77 -> 258.88146 | P62: =Assumption!P77 -> 286.5732
A63: Non-Current Tax Assets | B63: =Bal.sheet!B36 -> 13.22 | C63: =Bal.sheet!C36 -> 5.79 | D63: =Bal.sheet!D36 -> 17.8 | E63: =Bal.sheet!E36 -> 102.61 | F63: =Bal.sheet!F36 -> 151.29 | G63: =Bal.sheet!G36 -> 148.95 | H63: =Bal.sheet!H36 -> 78.32 | I63: =Bal.sheet!I36 -> 100.24 | ... K63: =Bal.sheet!K36 -> 89.68 | L63: =Assumption!L74 -> 99.272789 | M63: =Assumption!M74 -> 109.89169 | N63: =Assumption!N74 -> 121.64646 | O63: =Assumption!O74 -> 134.6586 | P63: =Assumption!P74 -> 149.06261
A64: Other non-current assets | B64: =Bal.sheet!B41 -> 1.54 | C64: =Bal.sheet!C41 -> 74.6 | D64: =Bal.sheet!D41 -> 54.09 | E64: =Bal.sheet!E41 -> 67.74 | F64: =Bal.sheet!F41 -> 68.12 | G64: =Bal.sheet!G41 -> 112.9 | H64: =Bal.sheet!H41 -> 79.51 | I64: =Bal.sheet!I41 -> 71.76 | ... K64: =Bal.sheet!K41 -> 131.5
A65: Total Non-Current Assets | B65: =B58+B59+B60+B61+B62+B63+B64 -> 3284.35 | C65: =C58+C59+C60+C61+C62+C63+C64 -> 4246.92 | D65: =D58+D59+D60+D61+D62+D63+D64 -> 4639.14 | E65: =E58+E59+E60+E61+E62+E63+E64 -> 4350.18 | F65: =F58+F59+F60+F61+F62+F63+F64 -> 4415.38 | G65: =G58+G59+G60+G61+G62+G63+G64 -> 5369.71 | H65: =H58+H59+H60+H61+H62+H63+H64 -> 6795.08 | I65: =I58+I59+I60+I61+I62+I63+I64 -> 7565.69 | ... P65: =P58+P59+P60+P61+P62+P63+P64 -> 10532.095
A67: Inventory | B67: =Bal.sheet!B25 -> 615.56 | C67: =Bal.sheet!C25 -> 599.27 | D67: =Bal.sheet!D25 -> 704.79 | E67: =Bal.sheet!E25 -> 732.9 | F67: =Bal.sheet!F25 -> 809.14 | G67: =Bal.sheet!G25 -> 1114.16 | H67: =Bal.sheet!H25 -> 1237.96 | I67: =Bal.sheet!I25 -> 1223.77 | ... K67: =Bal.sheet!K25 -> 1288.07 | L67: =Assumption!L61 -> 1406.851 | M67: =Assumption!M61 -> 1536.5855 | N67: =Assumption!N61 -> 1678.2836 | O67: =Assumption!O61 -> 1833.0486 | P67: =Assumption!P61 -> 2002.0854
A68: Trade receivable | B68: =Bal.sheet!B26 -> 420.69 | C68: =Bal.sheet!C26 -> 333.25 | D68: =Bal.sheet!D26 -> 321.34 | E68: =Bal.sheet!E26 -> 431.46 | F68: =Bal.sheet!F26 -> 379.63 | G68: =Bal.sheet!G26 -> 281.24 | H68: =Bal.sheet!H26 -> 454.55 | I68: =Bal.sheet!I26 -> 561.18 | ... K68: =Bal.sheet!K26 -> 600.58 | L68: =Assumption!L63 -> 655.03371 | M68: =Assumption!M63 -> 714.42467 | N68: =Assumption!N63 -> 779.20051 | O68: =Assumption!O63 -> 849.84948 | P68: =Assumption!P63 -> 926.9041
A69: Cash And Cash Equivalents | B69: =Bal.sheet!B27 -> 55.63 | C69: =Bal.sheet!C27 -> 26.16 | D69: =Bal.sheet!D27 -> 87.02 | E69: =Bal.sheet!E27 -> 124.71 | F69: =Bal.sheet!F27 -> 525.6 | G69: =Bal.sheet!G27 -> 834.74 | H69: =Bal.sheet!H27 -> 136.18 | I69: =Bal.sheet!I27 -> 33.4 | ... K69: =Bal.sheet!K27 -> 133.02 | L69: =Assumption!L64 -> 145.08073 | M69: =Assumption!M64 -> 158.23499 | N69: =Assumption!N64 -> 172.58192 | O69: =Assumption!O64 -> 188.22968 | P69: =Assumption!P64 -> 205.29619
A70: Short Term Loans And Advances | B70: =Bal.sheet!B28 -> 68.26 | C70: =Bal.sheet!C28 -> 91.81 | D70: =Bal.sheet!D28 -> 132.3 | E70: =Bal.sheet!E28 -> 109.88 | F70: =Bal.sheet!F28 -> 168.15 | G70: =Bal.sheet!G28 -> 148.71 | H70: =Bal.sheet!H28 -> 126.06 | I70: =Bal.sheet!I28 -> 140.4 | ... K70: =Bal.sheet!K28 -> 280.07 | L70: =Assumption!L65 -> 305.46354 | M70: =Assumption!M65 -> 333.15947 | N70: =Assumption!N65 -> 363.36656 | O70: =Assumption!O65 -> 396.31247 | P70: =Assumption!P65 -> 432.24555
A71: Other Short Term Financial Assets
A72: Current Tax Asset
A73: Assets held for sale
A74: Other Current Assets
A75: Total Current Assets | B75: =Bal.sheet!B29 -> 1160.14 | C75: =Bal.sheet!C29 -> 1050.49 | D75: =Bal.sheet!D29 -> 1245.45 | E75: =Bal.sheet!E29 -> 1398.95 | F75: =Bal.sheet!F29 -> 1882.52 | G75: =Bal.sheet!G29 -> 2378.85 | H75: =Bal.sheet!H29 -> 1954.75 | I75: =Bal.sheet!I29 -> 1958.75 | ... K75: =Bal.sheet!K29 -> 2301.74 | L75: =Assumption!L66 -> 2510.4354 | M75: =Assumption!M66 -> 2738.0529 | N75: =Assumption!N66 -> 2986.3082 | O75: =Assumption!O66 -> 3257.0724 | P75: =Assumption!P66 -> 3552.3864
A78: Total Assets | B78: =Bal.sheet!B43 -> 3231.51 | C78: =Bal.sheet!C43 -> 3992.86 | D78: =Bal.sheet!D43 -> 4567.76 | E78: =Bal.sheet!E43 -> 4336 | F78: =Bal.sheet!F43 -> 4784.23 | G78: =Bal.sheet!G43 -> 5628.01 | H78: =Bal.sheet!H43 -> 6484.87 | I78: =Bal.sheet!I43 -> 6964.96 | ... K78: =Bal.sheet!K43 -> 7866.5 | L78: =Assumption!L78 -> 7976.04 | M78: =Assumption!M78 -> 8085.58 | N78: =Assumption!N78 -> 8195.12 | O78: =Assumption!O78 -> 8304.66 | P78: =Assumption!P78 -> 8414.2
A80: Cash Flow Statement
A83: INR in Cr. | B83: 2016 | C83: 2017 | D83: 2018 | E83: 2019 | F83: 2020 | G83: 2021 | H83: 2022 | I83: 2023 | J83: 2024 | K83: 2025 | L83: 2026 | M83: 2027 | N83: 2028 | O83: 2029 | P83: 2030
A84: Profit before tax | B84: =cashflow!K6 -> 1209.35 | C84: =cashflow!J6 -> 1294.35 | D84: =cashflow!I6 -> 1373.13 | E84: =cashflow!H6 -> 1503.35 | F84: =cashflow!G6 -> 1408.47 | G84: =cashflow!F6 -> 1683.31 | H84: =cashflow!E6 -> 1896.31 | I84: =cashflow!D6 -> 1828.67 | J84: =cashflow!C6 -> 1966.7 | K84: =cashflow!B6 -> 1808.34 | L84: =Assumption!L25 -> 1887.55 | M84: =Assumption!M25 -> 1967.7081 | N84: =Assumption!N25 -> 2048.3321 | O84: =Assumption!O25 -> 2128.832 | P84: =Assumption!P25 -> 2208.4911
A85: Add: Depreciation | B85: =cashflow!K7 -> 72.83 | C85: =cashflow!J7 -> 75.43 | D85: =cashflow!I7 -> 102.5 | E85: =cashflow!H7 -> 108.83 | F85: =cashflow!G7 -> 129.93 | G85: =cashflow!F7 -> 143.4 | H85: =cashflow!E7 -> 160.39 | I85: =cashflow!D7 -> 188.29 | J85: =cashflow!C7 -> 208.86 | K85: =cashflow!B7 -> 250.93 | L85: =Assumption!L23 -> 288.7643 | M85: =Assumption!M23 -> 332.30313 | N85: =Assumption!N23 -> 382.40657 | O85: =Assumption!O23 -> 440.06443 | P85: =Assumption!P23 -> 506.41573
A86: Add: Finance Cost | B86: =PL!K19 -> 10.26 | C86: =PL!J19 -> 16.23 | D86: =PL!I19 -> 21.89 | E86: =PL!H19 -> 29.8 | F86: =PL!G19 -> 19.27 | G86: =PL!F19 -> 9.14 | H86: =PL!E19 -> 18.67 | I86: =PL!D19 -> 46.37 | J86: =PL!C19 -> 81.14 | K86: =PL!B19 -> 99.58 | L86: =Assumption!L19 -> 142.91224 | M86: =Assumption!M19 -> 205.1005 | N86: =Assumption!N19 -> 294.34999 | O86: =Assumption!O19 -> 422.43639 | P86: =Assumption!P19 -> 606.2596
A87: Cash Flow before Working Capital Changes | B87: =B84+B85+B86 -> 1292.44 | C87: =C84+C85+C86 -> 1386.01 | D87: =D84+D85+D86 -> 1497.52 | E87: =E84+E85+E86 -> 1641.98 | F87: =F84+F85+F86 -> 1557.67 | G87: =G84+G85+G86 -> 1835.85 | H87: =H84+H85+H86 -> 2075.37 | I87: =I84+I85+I86 -> 2063.33 | ... P87: =P84+P85+P86 -> 3321.1664
A88: Changes in working capital
A89: Inventories | B89: =cashflow!K19 -> -64.95 | C89: =cashflow!J19 -> 16.28 | D89: =cashflow!I19 -> -105.52 | E89: =cashflow!H19 -> -28.1 | F89: =cashflow!G19 -> -76.24 | G89: =cashflow!F19 -> -305.02 | H89: =cashflow!E19 -> -123.8 | I89: =cashflow!D19 -> 14.19 | J89: =cashflow!C19 -> 73.89 | K89: =cashflow!B19 -> -138.19 | L89: =Assumption!L85 -> 836.93004 | M89: =Assumption!M85 -> 134.61577 | N89: =Assumption!N85 -> 157.91962 | O89: =Assumption!O85 -> 184.68273 | P89: =Assumption!P85 -> 215.38206
A90: Trade Receivable | B90: =cashflow!K18 -> -78.59 | C90: =cashflow!J18 -> 87.43 | D90: =cashflow!I18 -> 10.82 | E90: =cashflow!H18 -> -112.39 | F90: =cashflow!G18 -> 53.94 | G90: =cashflow!F18 -> 94.27 | H90: =cashflow!E18 -> -176 | I90: =cashflow!D18 -> -113.54 | J90: =cashflow!C18 -> -158.17 | K90: =cashflow!B18 -> 115.22
A91: Other current assets | B91: =cashflow!K21 -> 0 | C91: =cashflow!J21 -> -24.96 | D91: =cashflow!I21 -> -90.17 | E91: =cashflow!H21 -> 67.91 | F91: =cashflow!G21 -> -52.16 | G91: =cashflow!F21 -> 96.39 | H91: =cashflow!E21 -> 34.37 | I91: =cashflow!D21 -> 42.95 | J91: =cashflow!C21 -> -66.58 | K91: =cashflow!B21 -> -87.93
A92: Trade payable | B92: =cashflow!K20 -> 204.25 | C92: =cashflow!J20 -> -24.18 | D92: =cashflow!I20 -> 31.57 | E92: =cashflow!H20 -> 37.75 | F92: =cashflow!G20 -> 33.4 | G92: =cashflow!F20 -> 448.92 | H92: =cashflow!E20 -> 100.66 | I92: =cashflow!D20 -> 237.83 | J92: =cashflow!C20 -> 240.2 | K92: =cashflow!B20 -> 282.45
A93: Other current liabilities
A94: Net Changes in working capital | B94: =cashflow!K22 -> 60.71 | C94: =cashflow!J22 -> 54.57 | D94: =cashflow!I22 -> -153.3 | E94: =cashflow!H22 -> -34.83 | F94: =cashflow!G22 -> -41.06 | G94: =cashflow!F22 -> 334.56 | H94: =cashflow!E22 -> -164.77 | I94: =cashflow!D22 -> 181.43 | J94: =cashflow!C22 -> 89.34 | K94: =cashflow!B22 -> 171.55
A95: Tax paid | B95: =cashflow!K25 -> -260.73 | C95: =cashflow!J25 -> -274.5 | D95: =cashflow!I25 -> -301.07 | E95: =cashflow!H25 -> -319.56 | F95: =cashflow!G25 -> -268.94 | G95: =cashflow!F25 -> -274.6 | H95: =cashflow!E25 -> -328.45 | I95: =cashflow!D25 -> -432.35 | J95: =cashflow!C25 -> -390.33 | K95: =cashflow!B25 -> -327.67 | L95: =-L27 -> 0 | M95: =-M27 -> 0 | N95: =-N27 -> 0 | O95: =-O27 -> 0 | P95: =-P27 -> 0
A96: Net cash flow from opreating | B96: =cashflow!K5 -> 960.3 | C96: =cashflow!J5 -> 926.94 | D96: =cashflow!I5 -> 816.41 | E96: =cashflow!H5 -> 1123.57 | F96: =cashflow!G5 -> 1154.77 | G96: =cashflow!F5 -> 1704.17 | H96: =cashflow!E5 -> 1319.95 | I96: =cashflow!D5 -> 1561.91 | J96: =cashflow!C5 -> 1653.33 | K96: =cashflow!B5 -> 1622.97 | L96: =L87+L89+L90+L91+L92+L93+L95 -> 3156.1566 | M96: =M87+M89+M90+M91+M92+M93+M95 -> 2639.7275 | N96: =N87+N89+N90+N91+N92+N93+N95 -> 2883.0083 | O96: =O87+O89+O90+O91+O92+O93+O95 -> 3176.0156 | P96: =P87+P89+P90+P91+P92+P93+P95 -> 3536.5485
A98: Capex | B98: =cashflow!K31 -> -106.84 | C98: =cashflow!J31 -> -411.12 | D98: =cashflow!I31 -> -110.74 | E98: =cashflow!H31 -> -125.28 | F98: =cashflow!G31 -> -264.54 | G98: =cashflow!F31 -> -249.9 | H98: =cashflow!E31 -> -296.77 | I98: =cashflow!D31 -> -410.05 | J98: =cashflow!C31 -> -456.55 | K98: =cashflow!B31 -> -351.78
A99: Net cash flow from investing acticituies | B99: =cashflow!K30 -> -494.33 | C99: =cashflow!J30 -> -678.94 | D99: =cashflow!I30 -> -261.18 | E99: =cashflow!H30 -> 417.78 | F99: =cashflow!G30 -> -330.28 | G99: =cashflow!F30 -> -1120.37 | H99: =cashflow!E30 -> -681.7 | I99: =cashflow!D30 -> -617.2 | J99: =cashflow!C30 -> -736.09 | K99: =cashflow!B30 -> -98.9
A101: Finace cost | B101: =PL!K19 -> 10.26 | C101: =PL!J19 -> 16.23 | D101: =PL!I19 -> 21.89 | E101: =PL!H19 -> 29.8 | F101: =PL!G19 -> 19.27 | G101: =PL!F19 -> 9.14 | H101: =PL!E19 -> 18.67 | I101: =PL!D19 -> 46.37 | J101: =PL!C19 -> 81.14 | K101: =PL!B19 -> 99.58 | L101: =Assumption!L19 -> 142.91224 | M101: =Assumption!M19 -> 205.1005 | N101: =Assumption!N19 -> 294.34999 | O101: =Assumption!O19 -> 422.43639 | P101: =Assumption!P19 -> 606.2596
A102: Dividend Paid | B102: =cashflow!K55 -> -351.12 | C102: =cashflow!J55 -> -396.34 | D102: =cashflow!I55 -> -396.34 | E102: =cashflow!H55 -> -1324.71 | F102: =cashflow!G55 -> -512.45 | G102: =cashflow!F55 -> -592.09 | H102: =cashflow!E55 -> -972.32 | I102: =cashflow!D55 -> -921.31 | J102: =cashflow!C55 -> -965.76 | K102: =cashflow!B55 -> -974.78 | L102: =Assumption!L34 -> 0 | M102: =Assumption!M34 -> 0 | N102: =Assumption!N34 -> 0 | O102: =Assumption!O34 -> 0 | P102: =Assumption!P34 -> 0
A103: Net cash flow from financing activities | B103: =cashflow!K46 -> -455.04 | C103: =cashflow!J46 -> -273.66 | D103: =cashflow!I46 -> -496.18 | E103: =cashflow!H46 -> -1619.39 | F103: =cashflow!G46 -> -826 | G103: =cashflow!F46 -> -555.04 | H103: =cashflow!E46 -> -634.79 | I103: =cashflow!D46 -> -939.83 | J103: =cashflow!C46 -> -921.82 | K103: =cashflow!B46 -> -1510.68 | L103: =-L101-L102 -> -142.91224 | M103: =-M101-M102 -> -205.1005 | N103: =-N101-N102 -> -294.34999 | O103: =-O101-O102 -> -422.43639 | P103: =-P101-P102 -> -606.2596
A105: Net changes in cash | B105: =cashflow!K59 -> 10.93 | C105: =cashflow!J59 -> -25.66 | D105: =cashflow!I59 -> 59.05 | E105: =cashflow!H59 -> -78.04 | F105: =cashflow!G59 -> -1.51 | G105: =cashflow!F59 -> 28.76 | H105: =cashflow!E59 -> 3.46 | I105: =cashflow!D59 -> 4.88 | J105: =cashflow!C59 -> -4.58 | K105: =cashflow!B59 -> 13.39 | L105: =L96+L99+L103 -> 3013.2444 | M105: =M96+M99+M103 -> 2434.6269 | N105: =N96+N99+N103 -> 2588.6583 | O105: =O96+O99+O103 -> 2753.5792 | P105: =P96+P99+P103 -> 2930.2889
A106: Add opening cash | B106: =cashflow!K4 -> 13.49 | C106: =cashflow!J4 -> 24.41 | D106: =cashflow!I4 -> -1.25 | E106: =cashflow!H4 -> 57.8 | F106: =cashflow!G4 -> -20.24 | G106: =cashflow!F4 -> -21.75 | H106: =cashflow!E4 -> 7.01 | I106: =cashflow!D4 -> 10.47 | J106: =cashflow!C4 -> 15.35 | K106: =cashflow!B4 -> 10.77 | L106: =K107 -> 24.16 | M106: =L107 -> 3037.4044 | N106: =M107 -> 5472.0313 | O106: =N107 -> 8060.6896 | P106: =O107 -> 10814.269
A107: Cash at the end | B107: =cashflow!K60 -> 24.42 | C107: =cashflow!J60 -> -1.25 | D107: =cashflow!I60 -> 57.8 | E107: =cashflow!H60 -> -20.24 | F107: =cashflow!G60 -> -21.75 | G107: =cashflow!F60 -> 7.01 | H107: =cashflow!E60 -> 10.47 | I107: =cashflow!D60 -> 15.35 | J107: =cashflow!C60 -> 10.77 | K107: =cashflow!B60 -> 24.16 | L107: =L105+L106 -> 3037.4044 | M107: =M105+M106 -> 5472.0313 | N107: =N105+N106 -> 8060.6896 | O107: =O105+O106 -> 10814.269 | P107: =P105+P106 -> 13744.558
A109: Check | B109: =B78-B56 -> 0 | C109: =C78-C56 -> 0 | D109: =D78-D56 -> 0 | E109: =E78-E56 -> 0 | F109: =F78-F56 -> 0 | G109: =G78-G56 -> 0 | H109: =H78-H56 -> 0 | I109: =I78-I56 -> 0 | ... P109: =P78-P56 -> 0

Sheet PPE Schedule
A1: PPE SCHEDULE | B1: ACTUAL PERIOD | L1: FORECASTED PERIOD
A3: INR in Cr. | B3: 2016 | C3: 2017 | D3: 2018 | E3: 2019 | F3: 2020 | G3: 2021 | H3: 2022 | I3: 2023 | J3: 2024 | K3: 2025 | L3: 2026 | M3: 2027 | N3: 2028 | O3: 2029 | P3: 2030
A4: Revenues | B4: =Assumption!B5 -> 5422.57 | C4: =Assumption!C5 -> 5369.84 | D4: =Assumption!D5 -> 5609.06 | E4: =Assumption!E5 -> 6273.19 | F4: =Assumption!F5 -> 6309.8 | G4: =Assumption!G5 -> 7184.73 | H4: =Assumption!H5 -> 8179.5 | I4: =Assumption!I5 -> 8684.35 | ... P4: =Assumption!P5 -> 12106.677
A5: Opening PP&E | C5: =Bal.sheet!B18 -> 638.81 | D5: =Bal.sheet!C18 -> 993.33 | E5: =Bal.sheet!D18 -> 1030.48 | F5: =Bal.sheet!E18 -> 1036.62 | G5: =Bal.sheet!F18 -> 1134.28 | H5: =Bal.sheet!G18 -> 1204.81 | I5: =Bal.sheet!H18 -> 1399 | J5: =Bal.sheet!I18 -> 1661.97 | K5: =Bal.sheet!J18 -> 1878.2 | L5: =K10 -> 2035.62 | M5: =L10 -> 2116.7794 | N5: =M10 -> 2176.3886 | O5: =N10 -> 2209.1899 | P5: =O10 -> 2209.0137
A6: Capex | B6: =-cashflow!K31 -> 106.84 | C6: =-cashflow!J31 -> 411.12 | D6: =-cashflow!I31 -> 110.74 | E6: =-cashflow!H31 -> 125.28 | F6: =-cashflow!G31 -> 264.54 | G6: =-cashflow!F31 -> 249.9 | H6: =-cashflow!E31 -> 296.77 | I6: =-cashflow!D31 -> 410.05 | J6: =-cashflow!C31 -> 456.55 | K6: =-cashflow!B31 -> 351.78 | L6: =L4*L7 -> 369.9237 | M6: =M4*M7 -> 391.9123 | N6: =N4*N7 -> 415.20792 | O6: =O4*O7 -> 439.88825 | P6: =P4*P7 -> 466.0356
A7: (% of revenues) | B7: =IF(B4=0,0,B6/B4) -> 0.019702835 | C7: =IF(C4=0,0,C6/C4) -> 0.07656094 | D7: =IF(D4=0,0,D6/D4) -> 0.019743059 | E7: =IF(E4=0,0,E6/E4) -> 0.019970701 | F7: =IF(F4=0,0,F6/F4) -> 0.041925259 | G7: =IF(G4=0,0,G6/G4) -> 0.0347821 | H7: =IF(H4=0,0,H6/H4) -> 0.036282169 | I7: =IF(I4=0,0,I6/I4) -> 0.04721712 | ... K7: =IF(K4=0,0,K6/K4) -> 0.03878197 | L7: =AVERAGE($B$7:$K$7) -> 0.038494098 | M7: =AVERAGE($B$7:$K$7) -> 0.038494098 | N7: =AVERAGE($B$7:$K$7) -> 0.038494098 | O7: =AVERAGE($B$7:$K$7) -> 0.038494098 | P7: =AVERAGE($B$7:$K$7) -> 0.038494098
A8: Depreciation | B8: =PL!K21 -> 72.83 | C8: =PL!J21 -> 75.43 | D8: =PL!I21 -> 102.5 | E8: =PL!H21 -> 108.83 | F8: =PL!G21 -> 129.93 | G8: =PL!F21 -> 143.4 | H8: =PL!E21 -> 160.39 | I8: =PL!D21 -> 188.29 | J8: =PL!C21 -> 208.86 | K8: =PL!B21 -> 250.93 | L8: =Assumption!L23 -> 288.7643 | M8: =Assumption!M23 -> 332.30313 | N8: =Assumption!N23 -> 382.40657 | O8: =Assumption!O23 -> 440.06443 | P8: =Assumption!P23 -> 506.41573
A9: (Depreceiation Rate %) | B9: =IF(B5=0,0,B8/B5) -> 0 | C9: =IF(C5=0,0,C8/C5) -> 0.11807893 | D9: =IF(D5=0,0,D8/D5) -> 0.10318827 | E9: =IF(E5=0,0,E8/E5) -> 0.10561098 | F9: =IF(F5=0,0,F8/F5) -> 0.12534005 | G9: =IF(G5=0,0,G8/G5) -> 0.12642381 | H9: =IF(H5=0,0,H8/H5) -> 0.13312473 | I9: =IF(I5=0,0,I8/I5) -> 0.13458899 | ... P9: =IF(P5=0,0,P8/P5) -> 0.2292497
A10: Ending PP&E | B10: =Bal.sheet!B18 -> 638.81 | C10: =Bal.sheet!C18 -> 993.33 | D10: =Bal.sheet!D18 -> 1030.48 | E10: =Bal.sheet!E18 -> 1036.62 | F10: =Bal.sheet!F18 -> 1134.28 | G10: =Bal.sheet!G18 -> 1204.81 | H10: =Bal.sheet!H18 -> 1399 | I10: =Bal.sheet!I18 -> 1661.97 | ... K10: =Bal.sheet!K18 -> 2035.62 | L10: =L5+L6-L8 -> 2116.7794 | M10: =M5+M6-M8 -> 2176.3886 | N10: =N5+N6-N8 -> 2209.1899 | O10: =O5+O6-O8 -> 2209.0137 | P10: =P5+P6-P8 -> 2168.6336

Sheet ratios
A1: RATIO | B1: 2016 | C1: 2017 | D1: 2018 | E1: 2019 | F1: 2020 | G1: 2021 | H1: 2022 | I1: 2023 | J1: 2024 | K1: 2025
A2: Liquidity Ratios
A3: Current Ratio | B3: =Assumption!B66/Assumption!B71 -> 1.0342694 | C3: =Assumption!C66/Assumption!C71 -> 0.93303905 | D3: =Assumption!D66/Assumption!D71 -> 1.0840275 | E3: =Assumption!E66/Assumption!E71 -> 1.1332485 | F3: =Assumption!F66/Assumption!F71 -> 1.4306168 | G3: =Assumption!G66/Assumption!G71 -> 1.2679423 | H3: =Assumption!H66/Assumption!H71 -> 0.9595796 | I3: =Assumption!I66/Assumption!I71 -> 0.84767951 | ... K3: =Assumption!K66/Assumption!K71 -> 0.76578657
A4: Quick Ratio | B4: =(Assumption!B66-Assumption!B61)/Assumption!B71 -> 0.48549523 | C4: =(Assumption!C66-Assumption!C61)/Assumption!C71 -> 0.40077095 | D4: =(Assumption!D66-Assumption!D61)/Assumption!D71 -> 0.47058516 | E4: =(Assumption!E66-Assumption!E61)/Assumption!E71 -> 0.53954766 | F4: =(Assumption!F66-Assumption!F61)/Assumption!F71 -> 0.81571268 | G4: =(Assumption!G66-Assumption!G61)/Assumption!G71 -> 0.67408789 | H4: =(Assumption!H66-Assumption!H61)/Assumption!H71 -> 0.35186958 | I4: =(Assumption!I66-Assumption!I61)/Assumption!I71 -> 0.31807402 | ... K4: =(Assumption!K66-Assumption!K61)/Assumption!K71 -> 0.33724698
A5: Profitability Ratios
A6: Gross Margin | B6: =Assumption!B21/Assumption!B7 -> 0.23542048 | C6: =Assumption!C21/Assumption!C7 -> 0.25469921 | D6: =Assumption!D21/Assumption!D7 -> 0.25965276 | E6: =Assumption!E21/Assumption!E7 -> 0.25740927 | F6: =Assumption!F21/Assumption!F7 -> 0.24114024 | G6: =Assumption!G21/Assumption!G7 -> 0.24814574 | H6: =Assumption!H21/Assumption!H7 -> 0.25057292 | I6: =Assumption!I21/Assumption!I7 -> 0.23158613 | ... K6: =Assumption!K21/Assumption!K7 -> 0.22734745
A7: Operating Margin | B7: =Assumption!B17/Assumption!B7 -> 0.2507886 | C7: =Assumption!C17/Assumption!C7 -> 0.24019576 | D7: =Assumption!D17/Assumption!D7 -> 0.23728465 | E7: =Assumption!E17/Assumption!E7 -> 0.23574747 | F7: =Assumption!F17/Assumption!F7 -> 0.23532962 | G7: =Assumption!G17/Assumption!G7 -> 0.22916848 | H7: =Assumption!H17/Assumption!H7 -> 0.229184 | I7: =Assumption!I17/Assumption!I7 -> 0.21493272 | ... K7: =Assumption!K17/Assumption!K7 -> 0.20473602
A8: Net Margin | B8: =Assumption!B33/Assumption!B7 -> 0.16836261 | C8: =Assumption!C33/Assumption!C7 -> 0.18575203 | D8: =Assumption!D33/Assumption!D7 -> 0.19024334 | E8: =Assumption!E33/Assumption!E7 -> 0.20175632 | F8: =Assumption!F33/Assumption!F7 -> 0.19437778 | G8: =Assumption!G33/Assumption!G7 -> 0.18763584 | H8: =Assumption!H33/Assumption!H7 -> 0.17463959 | I8: =Assumption!I33/Assumption!I7 -> 0.15880785 | ... K8: =Assumption!K33/Assumption!K7 -> 0.15502754
A9: ROE | B9: =Assumption!B33/Assumption!B47 -> 0.29633939 | C9: =Assumption!C33/Assumption!C47 -> 0.27310355 | D9: =Assumption!D33/Assumption!D47 -> 0.25578562 | E9: =Assumption!E33/Assumption!E47 -> 0.31838683 | F9: =Assumption!F33/Assumption!F47 -> 0.27109918 | G9: =Assumption!G33/Assumption!G47 -> 0.25620731 | H9: =Assumption!H33/Assumption!H47 -> 0.2444529 | I9: =Assumption!I33/Assumption!I47 -> 0.21999943 | ... K9: =Assumption!K33/Assumption!K47 -> 0.18916276
A10: ROA | B10: =Assumption!B33/Assumption!B78 -> 0.28375589 | C10: =Assumption!C33/Assumption!C78 -> 0.25019159 | D10: =Assumption!D33/Assumption!D78 -> 0.23669589 | E10: =Assumption!E33/Assumption!E78 -> 0.29142528 | F10: =Assumption!F33/Assumption!F78 -> 0.2591995 | G10: =Assumption!G33/Assumption!G78 -> 0.24542778 | H10: =Assumption!H33/Assumption!H78 -> 0.22104375 | I10: =Assumption!I33/Assumption!I78 -> 0.19858118 | ... K10: =Assumption!K33/Assumption!K78 -> 0.17850505
A11: ROCE | B11: =Assumption!B17/(Assumption!B78-Assumption!B71) -> 0.64739479 | C11: =Assumption!C17/(Assumption!C78-Assumption!C71) -> 0.45057168 | D11: =Assumption!D17/(Assumption!D78-Assumption!D71) -> 0.3944338 | E11: =Assumption!E17/(Assumption!E78-Assumption!E71) -> 0.47605706 | F11: =Assumption!F17/(Assumption!F78-Assumption!F71) -> 0.43286577 | G11: =Assumption!G17/(Assumption!G78-Assumption!G71) -> 0.44964631 | H11: =Assumption!H17/(Assumption!H78-Assumption!H71) -> 0.42293908 | I11: =Assumption!I17/(Assumption!I78-Assumption!I71) -> 0.40219671 | ... K11: =Assumption!K17/(Assumption!K78-Assumption!K71) -> 0.3815149
A12: Leverage Ratios
A13: Debt-Equity | B13: =Assumption!B49/Assumption!B47 -> 0.028190635 | C13: =Assumption!C49/Assumption!C47 -> 0.077572255 | D13: =Assumption!D49/Assumption!D47 -> 0.067806835 | E13: =Assumption!E49/Assumption!E47 -> 0.078073584 | F13: =Assumption!F49/Assumption!F47 -> 0.032934505 | G13: =Assumption!G49/Assumption!G47 -> 0.033363506 | H13: =Assumption!H49/Assumption!H47 -> 0.095530767 | I13: =Assumption!I49/Assumption!I47 -> 0.097895936 | ... K13: =Assumption!K49/Assumption!K47 -> 0.05101781
A14: Interest Coverage | B14: =Assumption!B17/Assumption!B19 -> 133.12671 | C14: =Assumption!C17/Assumption!C19 -> 79.592113 | D14: =Assumption!D17/Assumption!D19 -> 61.603929 | E14: =Assumption!E17/Assumption!E19 -> 49.547315 | F14: =Assumption!F17/Assumption!F19 -> 77.910223 | G14: =Assumption!G17/Assumption!G19 -> 184.5744 | H14: =Assumption!H17/Assumption!H19 -> 100.75736 | I14: =Assumption!I17/Assumption!I19 -> 40.369204 | ... K14: =Assumption!K17/Assumption!K19 -> 18.622816
A15: Efficiency Ratios
A16: Inventory Turnover | B16: =Assumption!B15/Assumption!B61 -> 6.6288583 | C16: =Assumption!C15/Assumption!C61 -> 6.8187128 | D16: =Assumption!D15/Assumption!D61 -> 6.1501724 | E16: =Assumption!E15/Assumption!E61 -> 6.5310274 | F16: =Assumption!F15/Assumption!F61 -> 6.0290679 | G16: =Assumption!G15/Assumption!G61 -> 5.0930118 | H16: =Assumption!H15/Assumption!H61 -> 5.1107063 | I16: =Assumption!I15/Assumption!I61 -> 5.5871692 | ... K16: =Assumption!K15/Assumption!K61 -> 5.5923591
A17: Receivable Turnover | B17: =Assumption!B7/Assumption!B63 -> 12.946207 | C17: =Assumption!C7/Assumption!C63 -> 16.138125 | D17: =Assumption!D7/Assumption!D63 -> 17.685598 | E17: =Assumption!E7/Assumption!E63 -> 14.516062 | F17: =Assumption!F7/Assumption!F63 -> 16.805021 | G17: =Assumption!G7/Assumption!G63 -> 26.17494 | H17: =Assumption!H7/Assumption!H63 -> 18.057397 | I17: =Assumption!I7/Assumption!I63 -> 15.519673 | ... K17: =Assumption!K7/Assumption!K63 -> 15.081771
A18: Payable Turnover | B18: =Assumption!B10/Assumption!B69 -> 2.0083018 | C18: =Assumption!C10/Assumption!C69 -> 2.0060582 | D18: =Assumption!D10/Assumption!D69 -> 2.1110289 | E18: =Assumption!E10/Assumption!E69 -> 2.1921801 | F18: =Assumption!F10/Assumption!F69 -> 2.1299416 | G18: =Assumption!G10/Assumption!G69 -> 1.7872415 | H18: =Assumption!H10/Assumption!H69 -> 1.8678152 | I18: =Assumption!I10/Assumption!I69 -> 1.801405 | ... K18: =Assumption!K10/Assumption!K69 -> 1.4630853
A19: Asset Turnover | B19: =Assumption!B7/Assumption!B78 -> 1.6853855 | C19: =Assumption!C7/Assumption!C78 -> 1.3469117 | D19: =Assumption!D7/Assumption!D78 -> 1.2441744 | E19: =Assumption!E7/Assumption!E78 -> 1.4444419 | F19: =Assumption!F7/Assumption!F78 -> 1.3334831 | G19: =Assumption!G7/Assumption!G78 -> 1.3080005 | H19: =Assumption!H7/Assumption!H78 -> 1.2657139 | I19: =Assumption!I7/Assumption!I78 -> 1.2504494 | ... K19: =Assumption!K7/Assumption!K78 -> 1.1514409
A20: Dividend Payout | B20: =Assumption!B34/Assumption!B33 -> 0.46152504 | C20: =Assumption!C34/Assumption!C33 -> 0.22041482 | D20: =Assumption!D34/Assumption!D33 -> 0.203659 | E20: =Assumption!E34/Assumption!E33 -> 0.17472816 | F20: =Assumption!F34/Assumption!F33 -> 0.1994968 | G20: =Assumption!G34/Assumption!G33 -> 0.22392436 | H20: =Assumption!H34/Assumption!H33 -> 0 | I20: =Assumption!I34/Assumption!I33 -> 0 | ... K20: =Assumption!K34/Assumption!K33 -> 0

Sheet beta
A1: Date | B1: Sensex | C1: Dabour | D1: Market Return | E1: Return on dabour | F1: Beta
A2: 40546 | B2: 20561.05 | C2: 100.7
A3: 40547 | B3: 20498.72 | C3: 102.75 | D3: -0.00304 | E3: 0.02015 | F3: =SLOPE(E3:E3719,D3:D3719) -> 0.51563123
A4: 40548 | B4: 20301.1 | C4: 103.05 | D4: -0.00969 | E4: 0.00292
A5: 40549 | B5: 20184.74 | C5: 101.35 | D5: -0.00575 | E5: -0.01663
A6: 40550 | B6: 19691.81 | C6: 100.1 | D6: -0.02472 | E6: -0.01241
A7: 40553 | B7: 19224.12 | C7: 101.3 | D7: -0.02404 | E7: 0.01192
A8: 40554 | B8: 19196.34 | C8: 102.85 | D8: -0.00145 | E8: 0.01519
A9: 40555 | B9: 19534.1 | C9: 101.75 | D9: 0.01744 | E9: -0.01075
A10: 40556 | B10: 19182.82 | C10: 100.8 | D10: -0.01815 | E10: -0.00938
A11: 40557 | B11: 18860.44 | C11: 100.75 | D11: -0.01695 | E11: -0.0005
A12: 40560 | B12: 18882.25 | C12: 99.1 | D12: 0.00116 | E12: -0.01651
A13: 40561 | B13: 19092.05 | C13: 101.25 | D13: 0.01105 | E13: 0.02146
A14: 40562 | B14: 18978.32 | C14: 100.25 | D14: -0.00597 | E14: -0.00993
A15: 40563 | B15: 19046.54 | C15: 99.6 | D15: 0.00359 | E15: -0.0065
... A3719: 46022 | B3719: 85220.6 | C3719: 503.3 | D3719: 0.00642 | E3719: 0.01532

Sheet Historicial beta
B2: Anticipated period | J2: Adjusted period
A4: Date | B4: Sensex | C4: Dabour | D4: Market Return | E4: Return on dabour | H4: Date | I4: Sensex | J4: Dabour | K4: Market Return | L4: Return on dabour | P4: Date | Q4: Sensex | R4: Dabour | S4: Market Return | T4: Return on dabour
A5: 42661 | B5: 28050.88 | C5: 275.15 | D5: 0.01874 | E5: 0.01243 | H5: 42683 | I5: 27252.53 | J5: 297.65 | K5: -0.01235 | L5: 0.0005 | P5: 42614 | Q5: 28423.48 | R5: 293.9 | S5: -0.00101 | T5: 0.01095
A6: 42662 | B6: 27984.37 | C6: 277.2 | D6: -0.00237 | E6: 0.00742 | H6: 42684 | I6: 27517.68 | J6: 296.6 | K6: 0.00968 | L6: -0.00353 | P6: 42615 | Q6: 28532.11 | R6: 296.7 | S6: 0.00381 | T6: 0.00948
A7: 42663 | B7: 28129.84 | C7: 280 | D7: 0.00518 | E7: 0.01005 | H7: 42685 | I7: 26818.82 | J7: 281.15 | K7: -0.02572 | L7: -0.0535 | P7: 42619 | Q7: 28978.02 | R7: 299.7 | S7: 0.01551 | T7: 0.01006
A8: 42664 | B8: 28077.18 | C8: 284.1 | D8: -0.00187 | E8: 0.01454 | H8: 42689 | I8: 26304.63 | J8: 270.35 | K8: -0.01936 | L8: -0.03917 | P8: 42620 | Q8: 28926.36 | R8: 297.05 | S8: -0.00178 | T8: -0.00888
A9: 42667 | B9: 28179.08 | C9: 283.35 | D9: 0.00362 | E9: -0.00264 | H9: 42690 | I9: 26298.69 | J9: 275.25 | K9: -0.00023 | L9: 0.01796 | P9: 42621 | Q9: 29045.28 | R9: 298.6 | S9: 0.0041 | T9: 0.0052
A10: 42668 | B10: 28091.42 | C10: 284.45 | D10: -0.00312 | E10: 0.00387 | H10: 42691 | I10: 26227.62 | J10: 276.6 | K10: -0.00271 | L10: 0.00489 | P10: 42622 | Q10: 28797.25 | R10: 293.7 | S10: -0.00858 | T10: -0.01655
A11: 42669 | B11: 27836.51 | C11: 296.4 | D11: -0.00912 | E11: 0.04115 | H11: 42692 | I11: 26150.24 | J11: 277.65 | K11: -0.00295 | L11: 0.00379 | P11: 42625 | Q11: 28353.54 | R11: 290.2 | S11: -0.01553 | T11: -0.01199
A12: 42670 | B12: 27915.9 | C12: 289.25 | D12: 0.00285 | E12: -0.02442 | H12: 42695 | I12: 25765.14 | J12: 275.75 | K12: -0.01484 | L12: -0.00687 | P12: 42627 | Q12: 28372.23 | R12: 292.65 | S12: 0.00066 | T12: 0.00841
A13: 42671 | B13: 27941.51 | C13: 290.9 | D13: 0.00092 | E13: 0.00569 | H13: 42696 | I13: 25960.78 | J13: 275.7 | K13: 0.00756 | L13: -0.00018 | P13: 42628 | Q13: 28412.89 | R13: 292.85 | S13: 0.00143 | T13: 0.00068
A14: 42673 | B14: 27930.21 | C14: 292.2 | D14: -0.0004 | E14: 0.00446 | H14: 42697 | I14: 26051.81 | J14: 280.6 | K14: 0.0035 | L14: 0.01762 | P14: 42629 | Q14: 28599.03 | R14: 292.8 | S14: 0.00653 | T14: -0.00017
A15: 42675 | B15: 27876.61 | C15: 290.05 | D15: -0.00192 | E15: -0.00739 | H15: 42698 | I15: 25860.17 | J15: 277.1 | K15: -0.00738 | L15: -0.01255 | P15: 42632 | Q15: 28634.5 | R15: 293.9 | S15: 0.00124 | T15: 0.00375
A16: 42676 | B16: 27527.22 | C16: 294.3 | D16: -0.01261 | E16: 0.01455 | H16: 42699 | I16: 26316.34 | J16: 276.05 | K16: 0.01749 | L16: -0.0038 | P16: 42633 | Q16: 28523.2 | R16: 291.15 | S16: -0.00389 | T16: -0.0094
... A19: 42681 | B19: 27458.99 | C19: 296.8 | D19: 0.00675 | E19: -0.00118 | H19: 42704 | I19: 26652.81 | J19: 283.35 | K19: 0.00976 | L19: 0.02194 | P19: 42636 | Q19: 28668.22 | R19: 282.7 | S19: -0.00365 | T19: -0.01178
A20: 42682 | B20: 27591.14 | C20: 297.5 | D20: 0.0048 | E20: 0.00236 | P20: 42639 | Q20: 28294.28 | R20: 281.3 | S20: -0.01313 | T20: -0.00496
P21: 42640 | Q21: 28223.7 | R21: 282 | S21: -0.0025 | T21: 0.00249
B22: Average Return | C22: =AVERAGE(E5:E20) -> 0.005658125 | D22: =AVERAGE(D5:D20) -> 0.000138125 | I22: Average Return | J22: =AVERAGE(L5:L19) -> -0.00325 | K22: =AVERAGE(K5:K19) -> -0.0023073333 | P22: 42641 | Q22: 28292.81 | R22: 277.4 | S22: 0.00245 | T22: -0.01645
B23: Alpha | C23: =INTERCEPT(E5:E20,D5:D20) -> 0.0057422721 | I23: Alpha | J23: =INTERCEPT(L5:L19,K5:K19) -> -0.00048232946 | P23: 42642 | Q23: 27827.53 | R23: 270.05 | S23: -0.01658 | T23: -0.02685
B24: Beta | C24: =SLOPE(E5:E20,D5:D20) -> -0.6092096 | I24: Beta | J24: =SLOPE(L5:L19,K5:K19) -> 1.1995105 | P24: 42643 | Q24: 27865.96 | R24: 271.3 | S24: 0.00138 | T24: 0.00462
P25: 42646 | Q25: 28243.29 | R25: 276.2 | S25: 0.01345 | T25: 0.0179
P26: 42647 | Q26: 28334.55 | R26: 280.05 | S26: 0.00323 | T26: 0.01384
P27: 42648 | Q27: 28220.98 | R27: 282.9 | S27: -0.00402 | T27: 0.01013
P28: 42649 | Q28: 28106.21 | R28: 285.9 | S28: -0.00408 | T28: 0.01055
P29: 42650 | Q29: 28061.14 | R29: 284 | S29: -0.0016 | T29: -0.00667
P30: 42653 | Q30: 28082.34 | R30: 285.55 | S30: 0.00076 | T30: 0.00544
P31: 42656 | Q31: 27643.11 | R31: 282.9 | S31: -0.01576 | T31: -0.00932
P32: 42657 | Q32: 27673.6 | R32: 279.7 | S32: 0.0011 | T32: -0.01138
P33: 42660 | Q33: 27529.97 | R33: 271.75 | S33: -0.0052 | T33: -0.02884
R36: Average Return | S36: =AVERAGE(T5:T33) -> -0.0023244828 | T36: =AVERAGE(S5:S33) -> -0.0011355172
R37: Alpha | S37: =INTERCEPT(T5:T33,S5:S33) -> -0.0013552973
R38: Beta | S38: =SLOPE(T5:T33,S5:S33) -> 0.85351892

Sheet Fundamental beta
A2: Debt to capital | B2: Debt to equity | C2: Levered Beta | D2: Unlev beta *(1+debt to equity % *(1-tax rate)))
A4: 0 | B4: 0 | C4: =$B$14*(1+B4*(1-B16)) -> 0.51563123
A5: 0.1 | B5: =A5/90% -> 0.11111111 | C5: =$B$14*(1+B5*(1-B17)) -> 0.57292359
A6: 0.25 | B6: =A6/75% -> 0.33333333 | C6: =$B$14*(1+B6*(1-D18)) -> 0.68750831
A7: 0.35 | B7: =A7/65% -> 0.53846154 | C7: =$B$14*(1+B7*(1-D19)) -> 0.79327882
A8: 0.5 | B8: =A8/50% -> 1 | C8: =$B$14*(1+B8*(1-D20)) -> 1.0312625
A9: 0.75 | B9: =A9/25% -> 3 | C9: =$B$14*(1+B9*(1-D21)) -> 2.0625249
A12: Years | B12: 2016 | C12: 2017 | D12: 2018 | E12: 2019 | F12: 2020 | G12: 2021 | H12: 2022 | I12: 2023 | J12: 2024 | K12: 2025
A13: DEBT to Equity | B13: =Bal.sheet!K11/Bal.sheet!K8 -> 0.05101781 | C13: =Bal.sheet!J11/Bal.sheet!J8 -> 0.11220802 | D13: =Bal.sheet!I11/Bal.sheet!I8 -> 0.097895936 | E13: =Bal.sheet!H11/Bal.sheet!H8 -> 0.095530767 | F13: =Bal.sheet!G11/Bal.sheet!G8 -> 0.033363506 | G13: =Bal.sheet!F11/Bal.sheet!F8 -> 0.032934505 | H13: =Bal.sheet!E11/Bal.sheet!E8 -> 0.078073584 | I13: =Bal.sheet!D11/Bal.sheet!D8 -> 0.067806835 | J13: =Bal.sheet!C11/Bal.sheet!C8 -> 0.077572255 | K13: =Bal.sheet!B11/Bal.sheet!B8 -> 0.028190635
A14: Unlevered Beta | B14: 0.51563123
A15: Levered Beta | B15: =$B$14*(1+B13*(1-B16)) -> 0.53630132 | C15: =$B$14*(1+C13*(1-C16)) -> 0.55959497 | D15: =$B$14*(1+D13*(1-D16)) -> 0.55359842 | E15: =$B$14*(1+E13*(1-E16)) -> 0.55279008 | F15: =$B$14*(1+F13*(1-F16)) -> 0.5276386 | G15: =$B$14*(1+G13*(1-G16)) -> 0.52958927 | H15: =$B$14*(1+H13*(1-H16)) -> 0.54784318 | I15: =$B$14*(1+I13*(1-I16)) -> 0.54249055 | ... K15: =$B$14*(1+K13*(1-K16)) -> 0.52700719 | L15: Unle beta x(1+debt to equity*(1-tax rate))
A16: Tax rate | B16: =Assumption!B27 -> 0.21425559 | C16: =Assumption!C27 -> 0.2401437 | D16: =Assumption!D27 -> 0.2478498 | E16: =Assumption!E27 -> 0.24563807 | F16: =Assumption!F27 -> 0.30202986 | G16: =Assumption!G27 -> 0.17807178 | H16: =Assumption!H27 -> 0.19984602 | I16: =Assumption!I27 -> 0.23178594 | ... K16: =Assumption!K27 -> 0.21739275

Sheet Accounting beta
A1: ROCE%
A2: Years | B2: Dabour India | C2: Average | E2: Dabur ROA
A3: 2025 | B3: =Assumption!K17/(Assumption!K78-Assumption!K71) -> 0.3815149 | C3: =AVERAGE(B3:B3) -> 0.3815149 | D3: ROA | E3: =Assumption!K33/Assumption!K78 -> 0.17850505
A4: 2024 | B4: =Assumption!J17/(Assumption!J78-Assumption!J71) -> 0.39094303 | C4: =AVERAGE(B4:B4) -> 0.39094303 | E4: =Assumption!J33/Assumption!J78 -> 0.19469483
A5: 2023 | B5: =Assumption!I17/(Assumption!I78-Assumption!I71) -> 0.40219671 | C5: =AVERAGE(B5:B5) -> 0.40219671 | E5: =Assumption!I33/Assumption!I78 -> 0.19858118
A6: 2022 | B6: =Assumption!H17/(Assumption!H78-Assumption!H71) -> 0.42293908 | C6: =AVERAGE(B6:B6) -> 0.42293908 | E6: =Assumption!H33/Assumption!H78 -> 0.22104375
A7: 2021 | B7: =Assumption!G17/(Assumption!G78-Assumption!G71) -> 0.44964631 | C7: =AVERAGE(B7:B7) -> 0.44964631 | E7: =Assumption!G33/Assumption!G78 -> 0.24542778
A8: 2020 | B8: =Assumption!F17/(Assumption!F78-Assumption!F71) -> 0.43286577 | C8: =AVERAGE(B8:B8) -> 0.43286577 | E8: =Assumption!F33/Assumption!F78 -> 0.2591995
A9: 2019 | B9: =Assumption!E17/(Assumption!E78-Assumption!E71) -> 0.47605706 | C9: =AVERAGE(B9:B9) -> 0.47605706 | E9: =Assumption!E33/Assumption!E78 -> 0.29142528
A10: 2018 | B10: =Assumption!D17/(Assumption!D78-Assumption!D71) -> 0.3944338 | C10: =AVERAGE(B10:B10) -> 0.3944338 | E10: =Assumption!D33/Assumption!D78 -> 0.23669589
A11: 2017 | B11: =Assumption!C17/(Assumption!C78-Assumption!C71) -> 0.45057168 | C11: =AVERAGE(B11:B11) -> 0.45057168 | E11: =Assumption!C33/Assumption!C78 -> 0.25019159
A12: 2016 | B12: =Assumption!B17/(Assumption!B78-Assumption!B71) -> 0.64739479 | C12: =AVERAGE(B12:B12) -> 0.64739479 | E12: =Assumption!B33/Assumption!B78 -> 0.28375589
B14: =VAR(B3:B12) -> 0.0059951241
B15: =COVAR(B3:B12,C3:C12) -> 0.0053956117
B16: =IF(B14=0,0,B15/B14) -> 0.9

Sheet WACC
A1: weighted average cost of capital
A2: INPUT | C2: Values | E2: Cost of Equity
A3: Risk Free Premium | B3: Rf | C3: 0.0669 | E3: Risk free rate (Rf) | F3: =C3 -> 0.0669
A4: Beta | B4: B | C4: =beta!F3 -> 0.51563123 | E4: Beta (Historical) | F4: =beta!F3 -> 0.51563123
A5: Market Return | B5: MR | C5: 0.12 | E5: Market risk premium (MRP) | F5: =C5-C3 -> 0.0531
A6: Cost of Equity | B6: Ke | C6: =C3+C4*(C5-C3) -> 0.094280019 | E6: Cost of Equity (Ke = Rf + β×MRP) | F6: =C6 -> 0.094280019
A7: Interest Expense | C7: =Assumption!K19 -> 99.58
A8: Total Debt | C8: =Assumption!K49 -> 378.72 | E8: Cost of Debt
A9: Cost of Debt | B9: Kd | C9: =C7/C8 -> 0.26293832 | E9: Interest Expense (INR Cr) | F9: =Assumption!K19 -> 99.58
A10: Tax Rate | B10: t | C10: =Assumption!K27 -> 0.21739275 | E10: Total Debt (INR Cr) | F10: =Assumption!K49 -> 378.72
A11: Total Equity | C11: =Assumption!K45+Assumption!K46 -> 7423.29 | E11: Cost of Debt (Kd = Interest/Debt) | F11: =IF(F10=0,0,F9/F10) -> 0.26293832
A12: Weight of Equity | C12: =C11/(C11+C8) -> 0.95145866 | E12: Tax Rate (t) | F12: =Assumption!K27 -> 0.21739275
A13: Weight of Debt | C13: =C8/(C8+C11) -> 0.048541337 | E13: Cost of Debt after tax [Kd×(1−t)] | F13: =F11*(1-F12) -> 0.20577744
A14: WACC | C14: =C12*C6+C13*C9*(1-C10) -> 0.099692252 | E14: Capital Structure
E15: Total Debt (INR Cr) | F15: =Assumption!K49 -> 378.72
E16: Total Equity (INR Cr) | F16: =Assumption!K47 -> 7423.29
E17: Total Capital (Debt + Equity) | F17: =F15+F16 -> 7802.01
E18: % of Debt (Weight of Debt) | F18: =IF(F17=0,0,F15/F17) -> 0.048541337
E19: % of Equity (Weight of Equity) | F19: =IF(F17=0,0,F16/F17) -> 0.95145866
E20: Debt to Equity Ratio | F20: =IF(F16=0,0,F15/F16) -> 0.05101781
E22: WACC = We×Ke + Wd×Kd×(1−t) | F22: =C14 -> 0.099692252

Sheet EVA
A1: EVA
A2: INPUT | C2: VALUE
A3: WACC | C3: =WACC!C14 -> 0.099692252
A4: TOTAL CAPITAL EMPLOYED | C4: =WACC!C8+WACC!C11 -> 7802.01
A5: EBIT | C5: =Assumption!K25+Assumption!K19 -> 1907.92
A6: TAX | C6: =Assumption!K27 -> 0.21739275
A7: NOPAT | C7: =C5*(1-C6) -> 1493.152
A8: EVA | C8: =C7-(C3*C4) -> 715.35208

Sheet DCF
A1: DCF VALUATION
A3: Assumptions/Base
A4: Tax Rate | B4: =WACC!C10 -> 0.21739275
A5: Discount Rate (WACC) | B5: =WACC!C14 -> 0.099692252
A6: Perpetural Growth Rate | B6: 0.04
A7: Valuation Date | B7: =TODAY() -> 46115
A8: Last Fiscal Year End | B8: 31-Mar-25
A9: Current Market Price | B9: 525
A10: Total Shares Outstanding (in Cr.) | B10: =Bal.sheet!K4 -> 177.23
A11: Debt (in Cr.) | B11: =Assumption!K49 -> 378.72 | M11: Intrinsic Value
A12: Cash (in Cr.) | B12: =Assumption!K64 -> 133.02 | M12: PV of Cash Flows | N12: =SUM(B28:F28) -> 3508.1409
M13: Continuing Value | N13: =G24 -> 19442.304
M14: PV of contuning value | N14: =G28 -> 12089.043
A15: Discounted Cash Flows | M15: Enterprise Value (in Cr) | N15: =N12+N14 -> 15597.184
A16: Year ˃ | G16: Perpetuity Growth | M16: Less: Debt (in Cr) | N16: =$B$11 -> 378.72
A17: Particulars | B17: 2026 | C17: 2027 | D17: 2028 | E17: 2029 | F17: 2030 | G17: Terminal Value | M17: Add: Cash (in Cr) | N17: =$B$12 -> 133.02
A18: EBIT | B18: ='financial satement'!L22 -> 1625.9091 | C18: ='financial satement'!M22 -> 1642.8425 | D18: ='financial satement'!N22 -> 1653.265 | E18: ='financial satement'!O22 -> 1655.955 | F18: ='financial satement'!P22 -> 1649.5121 | M18: Equity Value (in Cr) | N18: =N15-N16+N17 -> 15351.484
A19: Tax Rate | B19: =$B$4 -> 0.21739275 | C19: =$B$4 -> 0.21739275 | D19: =$B$4 -> 0.21739275 | E19: =$B$4 -> 0.21739275 | F19: =$B$4 -> 0.21739275 | M19: No. of share (in Cr.) | N19: =$B$10 -> 177.23
A20: NOPAT | B20: =B18*(1-B19) -> 1272.4483 | C20: =C18*(1-C19) -> 1285.7005 | D20: =D18*(1-D19) -> 1293.8572 | E20: =E18*(1-E19) -> 1295.9624 | F20: =F18*(1-F19) -> 1290.9201 | M20: Intrincsic value of share | N20: =N18/N19 -> 86.61899
A21: Add- Depreciation | B21: ='financial satement'!L21 -> 288.7643 | C21: ='financial satement'!M21 -> 332.30313 | D21: ='financial satement'!N21 -> 382.40657 | E21: ='financial satement'!O21 -> 440.06443 | F21: ='financial satement'!P21 -> 506.41573 | M21: Current share price | N21: =$B$9 -> 525
A22: Less-Capex | B22: ='PPE Schedule'!L6 -> 369.9237 | C22: ='PPE Schedule'!M6 -> 391.9123 | D22: ='PPE Schedule'!N6 -> 415.20792 | E22: ='PPE Schedule'!O6 -> 439.88825 | F22: ='PPE Schedule'!P6 -> 466.0356 | M22: No of shares | N22: =$B$10 -> 177.23
A23: Less-Net Changes In WC | B23: =Assumption!L85 -> 836.93004 | C23: =Assumption!M85 -> 134.61577 | D23: =Assumption!N85 -> 157.91962 | E23: =Assumption!O85 -> 184.68273 | F23: =Assumption!P85 -> 215.38206 | M23: Market capitalization (in Cr) | N23: =N22*N21 -> 93045.75
A24: Free Cash Flows | B24: =B20+B21-B22-B23 -> 354.35885 | C24: =C20+C21-C22-C23 -> 1091.4755 | D24: =D20+D21-D22-D23 -> 1103.1362 | E24: =E20+E21-E22-E23 -> 1111.4558 | F24: =F20+F21-F22-F23 -> 1115.9182 | G24: =F24*(1+$B$6)/($B$5-$B$6) -> 19442.304
A25: WACC | B25: =$B$5 -> 0.099692252 | C25: =$B$5 -> 0.099692252 | D25: =$B$5 -> 0.099692252 | E25: =$B$5 -> 0.099692252 | F25: =$B$5 -> 0.099692252 | G25: =$B$5 -> 0.099692252
A26: Growth | B26: 0 | C26: 0 | D26: 0 | E26: 0 | F26: 0 | G26: =$B$6 -> 0.04
A27: Discounting Factor | B27: =1/(1+$B$5)^1 -> 0.90934532 | C27: =1/(1+$B$5)^2 -> 0.82690891 | D27: =1/(1+$B$5)^3 -> 0.75194574 | E27: =1/(1+$B$5)^4 -> 0.68377834 | F27: =1/(1+$B$5)^5 -> 0.62179063 | G27: =1/(1+$B$5)^5 -> 0.62179063
A28: PV of Free Cash Flow | B28: =B24*B27 -> 322.23456 | C28: =C24*C27 -> 902.55085 | D28: =D24*D27 -> 829.49859 | E28: =E24*E27 -> 759.98942 | F28: =F24*F27 -> 693.86749 | G28: =G24*G27 -> 12089.043
A31: Market Value vs Fair Value
A32: CMP | B32: =$B$9 -> 525
A33: Upside Potential | B33: =N20-$B$9 -> -438.38101
A34: Fair Value | B34: =N20 -> 86.61899
A35: Upside Potential % | B35: =(B34-B32)/B32 -> -0.83501145
A36: Nature | B36: =IF(B35>0,"Undervalued","Overvalued") -> Overvalued
A37: Recommendation | B37: =IF(B35>0.1,"BUY",IF(B35<-0.1,"SELL","HOLD")) -> SELL

Sheet all ratios forcasted
A1: RATIOS
B3: previous year | F3: Forcasted year
A4: INR Cr. | B4: 2022 | C4: 2023 | D4: 2024 | E4: 2025 | F4: 2026 | G4: 2027 | H4: 2028 | I4: 2029 | J4: 2030
A6: Operating Income (%) | B6: =IF('financial satement'!G22=0,0,('financial satement'!H22-'financial satement'!G22)/'financial satement'!G22) -> 0.2446 | C6: =IF('financial satement'!H22=0,0,('financial satement'!I22-'financial satement'!H22)/'financial satement'!H22) -> -0.019310996 | D6: =IF('financial satement'!I22=0,0,('financial satement'!J22-'financial satement'!I22)/'financial satement'!I22) -> 0.13348756 | E6: =IF('financial satement'!J22=0,0,('financial satement'!K22-'financial satement'!J22)/'financial satement'!J22) -> -0.084023996 | F6: =IF('financial satement'!K22=0,0,('financial satement'!L22-'financial satement'!K22)/'financial satement'!K22) -> -0.15353383 | G6: =IF('financial satement'!L22=0,0,('financial satement'!M22-'financial satement'!L22)/'financial satement'!L22) -> 0.010414722 | H6: =IF('financial satement'!M22=0,0,('financial satement'!N22-'financial satement'!M22)/'financial satement'!M22) -> 0.0063441834 | I6: =IF('financial satement'!N22=0,0,('financial satement'!O22-'financial satement'!N22)/'financial satement'!N22) -> 0.0016270506 | J6: =IF('financial satement'!O22=0,0,('financial satement'!P22-'financial satement'!O22)/'financial satement'!O22) -> -0.0038907313
A7: EBITDA (%) | B7: =IF('financial satement'!G19=0,0,('financial satement'!H19-'financial satement'!G19)/'financial satement'!G19) -> 0.23369939 | C7: =IF('financial satement'!H19=0,0,('financial satement'!I19-'financial satement'!H19)/'financial satement'!H19) -> -0.0041673181 | D7: =IF('financial satement'!I19=0,0,('financial satement'!J19-'financial satement'!I19)/'financial satement'!I19) -> 0.13124831 | E7: =IF('financial satement'!J19=0,0,('financial satement'!K19-'financial satement'!J19)/'financial satement'!J19) -> -0.058168682 | F7: =IF('financial satement'!K19=0,0,('financial satement'!L19-'financial satement'!K19)/'financial satement'!K19) -> -0.118373 | G7: =IF('financial satement'!L19=0,0,('financial satement'!M19-'financial satement'!L19)/'financial satement'!L19) -> 0.031583565 | H7: =IF('financial satement'!M19=0,0,('financial satement'!N19-'financial satement'!M19)/'financial satement'!M19) -> 0.030643785 | I7: =IF('financial satement'!N19=0,0,('financial satement'!O19-'financial satement'!N19)/'financial satement'!N19) -> 0.029645157 | J7: =IF('financial satement'!O19=0,0,('financial satement'!P19-'financial satement'!O19)/'financial satement'!O19) -> 0.028581999
A8: Adj PAT (%) | B8: =IF('financial satement'!G29=0,0,('financial satement'!H29-'financial satement'!G29)/'financial satement'!G29) -> 0.1653363 | C8: =IF('financial satement'!H29=0,0,('financial satement'!I29-'financial satement'!H29)/'financial satement'!H29) -> -0.039987468 | D8: =IF('financial satement'!I29=0,0,('financial satement'!J29-'financial satement'!I29)/'financial satement'!I29) -> 0.15583558 | E8: =IF('financial satement'!J29=0,0,('financial satement'!K29-'financial satement'!J29)/'financial satement'!J29) -> -0.091292937 | F8: =IF('financial satement'!K29=0,0,('financial satement'!L29-'financial satement'!K29)/'financial satement'!K29) -> -0.0078408521 | G8: =IF('financial satement'!L29=0,0,('financial satement'!M29-'financial satement'!L29)/'financial satement'!L29) -> -0.33737742 | H8: =IF('financial satement'!M29=0,0,('financial satement'!N29-'financial satement'!M29)/'financial satement'!M29) -> -3.0774674 | I8: =IF('financial satement'!N29=0,0,('financial satement'!O29-'financial satement'!N29)/'financial satement'!N29) -> 9.4263869 | J8: =IF('financial satement'!O29=0,0,('financial satement'!P29-'financial satement'!O29)/'financial satement'!O29) -> 5.8441385
A9: Adj EPS (%) | B9: =IF('financial satement'!G38=0,0,IF('financial satement'!H38=0,0,(('financial satement'!H29/'financial satement'!H38)-('financial satement'!G29/'financial satement'!G38))/ABS('financial satement'!G29/'financial satement'!G38))) -> 0.16500672 | C9: =IF('financial satement'!H38=0,0,IF('financial satement'!I38=0,0,(('financial satement'!I29/'financial satement'!I38)-('financial satement'!H29/'financial satement'!H38))/ABS('financial satement'!H29/'financial satement'!H38))) -> -0.042100601 | D9: =IF('financial satement'!I38=0,0,IF('financial satement'!J38=0,0,(('financial satement'!J29/'financial satement'!J38)-('financial satement'!I29/'financial satement'!I38))/ABS('financial satement'!I29/'financial satement'!I38))) -> 0.15570513 | E9: =IF('financial satement'!J38=0,0,IF('financial satement'!K38=0,0,(('financial satement'!K29/'financial satement'!K38)-('financial satement'!J29/'financial satement'!J38))/ABS('financial satement'!J29/'financial satement'!J38))) -> -0.091446755 | F9: =IF('financial satement'!K38=0,0,IF('financial satement'!L38=0,0,(('financial satement'!L29/'financial satement'!L38)-('financial satement'!K29/'financial satement'!K38))/ABS('financial satement'!K29/'financial satement'!K38))) -> -0.0076728793 | G9: =IF('financial satement'!L38=0,0,IF('financial satement'!M38=0,0,(('financial satement'!M29/'financial satement'!M38)-('financial satement'!L29/'financial satement'!L38))/ABS('financial satement'!L29/'financial satement'!L38))) -> -0.33737742 | H9: =IF('financial satement'!M38=0,0,IF('financial satement'!N38=0,0,(('financial satement'!N29/'financial satement'!N38)-('financial satement'!M29/'financial satement'!M38))/ABS('financial satement'!M29/'financial satement'!M38))) -> -3.0774674 | I9: =IF('financial satement'!N38=0,0,IF('financial satement'!O38=0,0,(('financial satement'!O29/'financial satement'!O38)-('financial satement'!N29/'financial satement'!N38))/ABS('financial satement'!N29/'financial satement'!N38))) -> -9.4263869 | J9: =IF('financial satement'!O38=0,0,IF('financial satement'!P38=0,0,(('financial satement'!P29/'financial satement'!P38)-('financial satement'!O29/'financial satement'!O38))/ABS('financial satement'!O29/'financial satement'!O38))) -> -5.8441385
A11: Profitability
A12: EBITDA Margin (%) | B12: =IF('financial satement'!H7=0,0,'financial satement'!H19/'financial satement'!H7) -> 0.25024513 | C12: =IF('financial satement'!I7=0,0,'financial satement'!I19/'financial satement'!I7) -> 0.23471532 | D12: =IF('financial satement'!J7=0,0,'financial satement'!J19/'financial satement'!J7) -> 0.25240597 | E12: =IF('financial satement'!K7=0,0,'financial satement'!K19/'financial satement'!K7) -> 0.23942448 | F12: =IF('financial satement'!L7=0,0,'financial satement'!L19/'financial satement'!L7) -> 0.19924008 | G12: =IF('financial satement'!M7=0,0,'financial satement'!M19/'financial satement'!M7) -> 0.19400118 | H12: =IF('financial satement'!N7=0,0,'financial satement'!N19/'financial satement'!N7) -> 0.18872796 | I12: =IF('financial satement'!O7=0,0,'financial satement'!O19/'financial satement'!O7) -> 0.18342017 | J12: =IF('financial satement'!P7=0,0,'financial satement'!P19/'financial satement'!P7) -> 0.17807759
A13: Operating Income | B13: ='financial satement'!H22 -> 1886.49 | C13: ='financial satement'!I22 -> 1850.06 | D13: ='financial satement'!J22 -> 2097.02 | E13: ='financial satement'!K22 -> 1920.82 | F13: ='financial satement'!L22 -> 1625.9091 | G13: ='financial satement'!M22 -> 1642.8425 | H13: ='financial satement'!N22 -> 1653.265 | I13: ='financial satement'!O22 -> 1655.955 | J13: ='financial satement'!P22 -> 1649.5121
A14: EBIT Margin (%) | B14: =IF('financial satement'!H7=0,0,'financial satement'!H22/'financial satement'!H7) -> 0.23063635 | C14: =IF('financial satement'!I7=0,0,'financial satement'!I22/'financial satement'!I7) -> 0.21303379 | D14: =IF('financial satement'!J7=0,0,'financial satement'!J22/'financial satement'!J7) -> 0.22954376 | E14: =IF('financial satement'!K7=0,0,'financial satement'!K22/'financial satement'!K7) -> 0.21176071 | F14: =IF('financial satement'!L7=0,0,'financial satement'!L22/'financial satement'!L7) -> 0.16919139 | G14: =IF('financial satement'!M7=0,0,'financial satement'!M22/'financial satement'!M7) -> 0.16136197 | H14: =IF('financial satement'!N7=0,0,'financial satement'!N22/'financial satement'!N7) -> 0.15327488 | I14: =IF('financial satement'!O7=0,0,'financial satement'!O22/'financial satement'!O7) -> 0.14491065 | J14: =IF('financial satement'!P7=0,0,'financial satement'!P22/'financial satement'!P7) -> 0.13624813
A15: PAT | B15: ='financial satement'!H29 -> 1404.44 | C15: ='financial satement'!I29 -> 1348.28 | D15: ='financial satement'!J29 -> 1558.39 | E15: ='financial satement'!K29 -> 1416.12 | F15: ='financial satement'!L29 -> 1405.0164 | G15: ='financial satement'!M29 -> 930.9956 | H15: ='financial satement'!N29 -> -1934.113 | I15: ='financial satement'!O29 -> -20165.81 | J15: ='financial satement'!P29 -> -138017.6
A16: PAT Margin (%) | B16: =IF('financial satement'!H7=0,0,'financial satement'!H29/'financial satement'!H7) -> 0.17170243 | C16: =IF('financial satement'!I7=0,0,'financial satement'!I29/'financial satement'!I7) -> 0.15525399 | D16: =IF('financial satement'!J7=0,0,'financial satement'!J29/'financial satement'!J7) -> 0.17058431 | E16: =IF('financial satement'!K7=0,0,'financial satement'!K29/'financial satement'!K7) -> 0.15612008 | F16: =IF('financial satement'!L7=0,0,'financial satement'!L29/'financial satement'!L7) -> 0.14620539 | G16: =IF('financial satement'!M7=0,0,'financial satement'!M29/'financial satement'!M7) -> 0.091443508 | H16: =IF('financial satement'!N7=0,0,'financial satement'!N29/'financial satement'!N7) -> -0.17931241 | I16: =IF('financial satement'!O7=0,0,'financial satement'!O29/'financial satement'!O7) -> -1.7646861 | J16: =IF('financial satement'!P7=0,0,'financial satement'!P29/'financial satement'!P7) -> -11.400122
A17: ROE (%) | B17: =IF('financial satement'!H41=0,0,'financial satement'!H29/'financial satement'!H41) -> 0.23950736 | C17: =IF('financial satement'!I41=0,0,'financial satement'!I29/'financial satement'!I41) -> 0.21445932 | D17: =IF('financial satement'!J41=0,0,'financial satement'!J29/'financial satement'!J41) -> 0.22535164 | E17: =IF('financial satement'!K41=0,0,'financial satement'!K29/'financial satement'!K41) -> 0.19076717 | F17: =IF('financial satement'!L41=0,0,'financial satement'!L29/'financial satement'!L41) -> 8.1825192e-05 | G17: =IF('financial satement'!M41=0,0,'financial satement'!M29/'financial satement'!M41) -> 2.2880725e-08 | H17: =IF('financial satement'!N41=0,0,'financial satement'!N29/'financial satement'!N41) -> -2.0059312e-11 | I17: =IF('financial satement'!O41=0,0,'financial satement'!O29/'financial satement'!O41) -> -8.8259593e-14 | J17: =IF('financial satement'!P41=0,0,'financial satement'!P29/'financial satement'!P41) -> -2.5491345e-16
A18: ROCE (%) | B18: =IF(('financial satement'!H78-'financial satement'!H54)=0,0,'financial satement'!H22/('financial satement'!H78-'financial satement'!H54)) -> 0.42414193 | C18: =IF(('financial satement'!I78-'financial satement'!I54)=0,0,'financial satement'!I22/('financial satement'!I78-'financial satement'!I54)) -> 0.39749991 | D18: =IF(('financial satement'!J78-'financial satement'!J54)=0,0,'financial satement'!J22/('financial satement'!J78-'financial satement'!J54)) -> 0.41266843 | E18: =IF(('financial satement'!K78-'financial satement'!K54)=0,0,'financial satement'!K22/('financial satement'!K78-'financial satement'!K54)) -> 0.39516703 | F18: =IF(('financial satement'!L78-'financial satement'!L54)=0,0,'financial satement'!L22/('financial satement'!L78-'financial satement'!L54)) -> 0.35302079 | G18: =IF(('financial satement'!M78-'financial satement'!M54)=0,0,'financial satement'!M22/('financial satement'!M78-'financial satement'!M54)) -> 0.3814889 | H18: =IF(('financial satement'!N78-'financial satement'!N54)=0,0,'financial satement'!N22/('financial satement'!N78-'financial satement'!N54)) -> 0.41775559 | I18: =IF(('financial satement'!O78-'financial satement'!O54)=0,0,'financial satement'!O22/('financial satement'!O78-'financial satement'!O54)) -> 0.46607525 | J18: =IF(('financial satement'!P78-'financial satement'!P54)=0,0,'financial satement'!P22/('financial satement'!P78-'financial satement'!P54)) -> 0.53449676
A20: Valuations
A21: Price-earnings | B21: =IF(('financial satement'!H29/'financial satement'!H38)=0,0,DCF!$B$9/('financial satement'!H29/'financial satement'!H38)) -> 66.086661 | C21: =IF(('financial satement'!I29/'financial satement'!I38)=0,0,DCF!$B$9/('financial satement'!I29/'financial satement'!I38)) -> 68.991233 | D21: =IF(('financial satement'!J29/'financial satement'!J38)=0,0,DCF!$B$9/('financial satement'!J29/'financial satement'!J38)) -> 59.696225 | E21: =IF(('financial satement'!K29/'financial satement'!K38)=0,0,DCF!$B$9/('financial satement'!K29/'financial satement'!K38)) -> 65.704707 | F21: =IF(('financial satement'!L29/'financial satement'!L38)=0,0,DCF!$B$9/('financial satement'!L29/'financial satement'!L38)) -> 66.21275 | G21: =IF(('financial satement'!M29/'financial satement'!M38)=0,0,DCF!$B$9/('financial satement'!M29/'financial satement'!M38)) -> 99.925284 | H21: =IF(('financial satement'!N29/'financial satement'!N38)=0,0,DCF!$B$9/('financial satement'!N29/'financial satement'!N38)) -> -48.099568 | I21: =IF(('financial satement'!O29/'financial satement'!O38)=0,0,DCF!$B$9/('financial satement'!O29/'financial satement'!O38)) -> -4.6132537 | J21: =IF(('financial satement'!P29/'financial satement'!P38)=0,0,DCF!$B$9/('financial satement'!P29/'financial satement'!P38)) -> -0.67404448
A22: Price-book | B22: =IF(('financial satement'!H41/'financial satement'!H38)=0,0,DCF!$B$9/('financial satement'!H41/'financial satement'!H38)) -> 15.828241 | C22: =IF(('financial satement'!I41/'financial satement'!I38)=0,0,DCF!$B$9/('financial satement'!I41/'financial satement'!I38)) -> 14.795813 | D22: =IF(('financial satement'!J41/'financial satement'!J38)=0,0,DCF!$B$9/('financial satement'!J41/'financial satement'!J38)) -> 13.452642 | E22: =IF(('financial satement'!K41/'financial satement'!K38)=0,0,DCF!$B$9/('financial satement'!K41/'financial satement'!K38)) -> 12.534301 | F22: =IF(('financial satement'!L41/'financial satement'!L38)=0,0,DCF!$B$9/('financial satement'!L41/'financial satement'!L38)) -> 0.0054178709 | G22: =IF(('financial satement'!M41/'financial satement'!M38)=0,0,DCF!$B$9/('financial satement'!M41/'financial satement'!M38)) -> 2.286363e-06 | H22: =IF(('financial satement'!N41/'financial satement'!N38)=0,0,DCF!$B$9/('financial satement'!N41/'financial satement'!N38)) -> 9.6484427e-10 | I22: =IF(('financial satement'!O41/'financial satement'!O38)=0,0,DCF!$B$9/('financial satement'!O41/'financial satement'!O38)) -> 4.071639e-13 | J22: =IF(('financial satement'!P41/'financial satement'!P38)=0,0,DCF!$B$9/('financial satement'!P41/'financial satement'!P38)) -> 1.71823e-16
A23: EV/EBITDA | B23: =IF('financial satement'!H19=0,0,(DCF!$B$9*'financial satement'!H38+Assumption!H49-Assumption!H64)/'financial satement'!H19) -> 45.551644 | C23: =IF('financial satement'!I19=0,0,(DCF!$B$9*'financial satement'!I38+Assumption!I49-Assumption!I64)/'financial satement'!I19) -> 45.920259 | D23: =IF('financial satement'!J19=0,0,(DCF!$B$9*'financial satement'!J38+Assumption!J49-Assumption!J64)/'financial satement'!J19) -> 40.650359 | E23: =IF('financial satement'!K19=0,0,(DCF!$B$9*'financial satement'!K38+Assumption!K49-Assumption!K64)/'financial satement'!K19) -> 42.956809 | F23: =IF('financial satement'!L19=0,0,(DCF!$B$9*'financial satement'!L38+Assumption!L49-Assumption!L64)/'financial satement'!L19) -> 48.797551 | G23: =IF('financial satement'!M19=0,0,(DCF!$B$9*'financial satement'!M38+Assumption!M49-Assumption!M64)/'financial satement'!M19) -> 47.419413 | H23: =IF('financial satement'!N19=0,0,(DCF!$B$9*'financial satement'!N38+Assumption!N49-Assumption!N64)/'financial satement'!N19) -> 46.174012 | I23: =IF('financial satement'!O19=0,0,(DCF!$B$9*'financial satement'!O38+Assumption!O49-Assumption!O64)/'financial satement'!O19) -> 45.077527 | J23: =IF('financial satement'!P19=0,0,(DCF!$B$9*'financial satement'!P38+Assumption!P49-Assumption!P64)/'financial satement'!P19) -> 44.154249
A24: EV/Sales | B24: =IF('financial satement'!H7=0,0,(DCF!$B$9*'financial satement'!H38+Assumption!H49-Assumption!H64)/'financial satement'!H7) -> 11.399077 | C24: =IF('financial satement'!I7=0,0,(DCF!$B$9*'financial satement'!I38+Assumption!I49-Assumption!I64)/'financial satement'!I7) -> 10.778188 | D24: =IF('financial satement'!J7=0,0,(DCF!$B$9*'financial satement'!J38+Assumption!J49-Assumption!J64)/'financial satement'!J7) -> 10.260393 | E24: =IF('financial satement'!K7=0,0,(DCF!$B$9*'financial satement'!K38+Assumption!K49-Assumption!K64)/'financial satement'!K7) -> 10.284912 | F24: =IF('financial satement'!L7=0,0,(DCF!$B$9*'financial satement'!L38+Assumption!L49-Assumption!L64)/'financial satement'!L7) -> 9.7224278 | G24: =IF('financial satement'!M7=0,0,(DCF!$B$9*'financial satement'!M38+Assumption!M49-Assumption!M64)/'financial satement'!M7) -> 9.1994223 | H24: =IF('financial satement'!N7=0,0,(DCF!$B$9*'financial satement'!N38+Assumption!N49-Assumption!N64)/'financial satement'!N7) -> 8.7143268 | I24: =IF('financial satement'!O7=0,0,(DCF!$B$9*'financial satement'!O38+Assumption!O49-Assumption!O64)/'financial satement'!O7) -> 8.2681274 | J24: =IF('financial satement'!P7=0,0,(DCF!$B$9*'financial satement'!P38+Assumption!P49-Assumption!P64)/'financial satement'!P7) -> 7.8628822
A25: Dividend payout ratio (%) | B25: =IF('financial satement'!H29=0,0,'financial satement'!H31/'financial satement'!H29) -> 0 | C25: =IF('financial satement'!I29=0,0,'financial satement'!I31/'financial satement'!I29) -> 0 | D25: =IF('financial satement'!J29=0,0,'financial satement'!J31/'financial satement'!J29) -> 0 | E25: =IF('financial satement'!K29=0,0,'financial satement'!K31/'financial satement'!K29) -> 0 | F25: =IF('financial satement'!L29=0,0,'financial satement'!L31/'financial satement'!L29) -> 0 | G25: =IF('financial satement'!M29=0,0,'financial satement'!M31/'financial satement'!M29) -> 0 | H25: =IF('financial satement'!N29=0,0,'financial satement'!N31/'financial satement'!N29) -> 0 | I25: =IF('financial satement'!O29=0,0,'financial satement'!O31/'financial satement'!O29) -> 0 | J25: =IF('financial satement'!P29=0,0,'financial satement'!P31/'financial satement'!P29) -> 0
A26: Dividend yield (%) | B26: =IF(DCF!$B$9=0,0,IF('financial satement'!H38=0,0,('financial satement'!H31/'financial satement'!H38)/DCF!$B$9)) -> 0 | C26: =IF(DCF!$B$9=0,0,IF('financial satement'!I38=0,0,('financial satement'!I31/'financial satement'!I38)/DCF!$B$9)) -> 0 | D26: =IF(DCF!$B$9=0,0,IF('financial satement'!J38=0,0,('financial satement'!J31/'financial satement'!J38)/DCF!$B$9)) -> 0 | E26: =IF(DCF!$B$9=0,0,IF('financial satement'!K38=0,0,('financial satement'!K31/'financial satement'!K38)/DCF!$B$9)) -> 0 | F26: =IF(DCF!$B$9=0,0,IF('financial satement'!L38=0,0,('financial satement'!L31/'financial satement'!L38)/DCF!$B$9)) -> 0 | G26: =IF(DCF!$B$9=0,0,IF('financial satement'!M38=0,0,('financial satement'!M31/'financial satement'!M38)/DCF!$B$9)) -> 0 | H26: =IF(DCF!$B$9=0,0,IF('financial satement'!N38=0,0,('financial satement'!N31/'financial satement'!N38)/DCF!$B$9)) -> 0 | I26: =IF(DCF!$B$9=0,0,IF('financial satement'!O38=0,0,('financial satement'!O31/'financial satement'!O38)/DCF!$B$9)) -> 0 | J26: =IF(DCF!$B$9=0,0,IF('financial satement'!P38=0,0,('financial satement'!P31/'financial satement'!P38)/DCF!$B$9)) -> 0
A28: B/S ratios
A29: Inventory days | B29: =IF(Assumption!H15=0,0,Assumption!H61*365/Assumption!H15) -> 71.4187 | C29: =IF(Assumption!I15=0,0,Assumption!I61*365/Assumption!I15) -> 65.328253 | D29: =IF(Assumption!J15=0,0,Assumption!J61*365/Assumption!J15) -> 59.115215 | E29: =IF(Assumption!K15=0,0,Assumption!K61*365/Assumption!K15) -> 65.267625 | F29: =IF(Assumption!L15=0,0,Assumption!L61*365/Assumption!L15) -> 66.848645 | G29: =IF(Assumption!M15=0,0,Assumption!M61*365/Assumption!M15) -> 68.467963 | H29: =IF(Assumption!N15=0,0,Assumption!N61*365/Assumption!N15) -> 70.126507 | I29: =IF(Assumption!O15=0,0,Assumption!O61*365/Assumption!O15) -> 71.825226 | J29: =IF(Assumption!P15=0,0,Assumption!P61*365/Assumption!P15) -> 73.565095
A30: Creditor days | B30: =IF(Assumption!H10=0,0,Assumption!H69*365/Assumption!H10) -> 195.41548 | C30: =IF(Assumption!I10=0,0,Assumption!I69*365/Assumption!I10) -> 202.61962 | D30: =IF(Assumption!J10=0,0,Assumption!J69*365/Assumption!J10) -> 230.3835 | E30: =IF(Assumption!K10=0,0,Assumption!K69*365/Assumption!K10) -> 249.47281 | F30: =IF(Assumption!L10=0,0,Assumption!L69*365/Assumption!L10) -> 262.32164 | G30: =IF(Assumption!M10=0,0,Assumption!M69*365/Assumption!M10) -> 275.83222 | H30: =IF(Assumption!N10=0,0,Assumption!N69*365/Assumption!N10) -> 290.03866 | I30: =IF(Assumption!O10=0,0,Assumption!O69*365/Assumption!O10) -> 304.97678 | J30: =IF(Assumption!P10=0,0,Assumption!P69*365/Assumption!P10) -> 320.68428
A31: Debtor days | B31: =IF(Assumption!H7=0,0,Assumption!H63*365/Assumption!H7) -> 20.213323 | C31: =IF(Assumption!I7=0,0,Assumption!I63*365/Assumption!I7) -> 23.518537 | D31: =IF(Assumption!J7=0,0,Assumption!J63*365/Assumption!J7) -> 28.890548 | E31: =IF(Assumption!K7=0,0,Assumption!K63*365/Assumption!K7) -> 24.201402 | F31: =IF(Assumption!L7=0,0,Assumption!L63*365/Assumption!L7) -> 24.87932 | G31: =IF(Assumption!M7=0,0,Assumption!M63*365/Assumption!M7) -> 25.612652 | H31: =IF(Assumption!N7=0,0,Assumption!N63*365/Assumption!N7) -> 26.3676 | I31: =IF(Assumption!O7=0,0,Assumption!O63*365/Assumption!O7) -> 27.144801 | J31: =IF(Assumption!P7=0,0,Assumption!P63*365/Assumption!P7) -> 27.94491
A32: Asset turnover | B32: =IF('financial satement'!H78=0,0,'financial satement'!H7/'financial satement'!H78) -> 1.2613206 | C32: =IF('financial satement'!I78=0,0,'financial satement'!I7/'financial satement'!I78) -> 1.2468629 | D32: =IF('financial satement'!J78=0,0,'financial satement'!J7/'financial satement'!J78) -> 1.1777294 | E32: =IF('financial satement'!K78=0,0,'financial satement'!K7/'financial satement'!K78) -> 1.1530808 | F32: =IF('financial satement'!L78=0,0,'financial satement'!L7/'financial satement'!L78) -> 1.2048436 | G32: =IF('financial satement'!M78=0,0,'financial satement'!M7/'financial satement'!M78) -> 1.2591677 | H32: =IF('financial satement'!N78=0,0,'financial satement'!N7/'financial satement'!N78) -> 1.3161827 | I32: =IF('financial satement'!O78=0,0,'financial satement'!O7/'financial satement'!O78) -> 1.3760251 | J32: =IF('financial satement'!P78=0,0,'financial satement'!P7/'financial satement'!P78) -> 1.4388387
A33: Current ratio | B33: =IF(Assumption!H71=0,0,Assumption!H66/Assumption!H71) -> 0.9595796 | C33: =IF(Assumption!I71=0,0,Assumption!I66/Assumption!I71) -> 0.84767951 | D33: =IF(Assumption!J71=0,0,Assumption!J66/Assumption!J71) -> 0.81193115 | E33: =IF(Assumption!K71=0,0,Assumption!K66/Assumption!K71) -> 0.76578657 | F33: =IF(Assumption!L71=0,0,Assumption!L66/Assumption!L71) -> 0.74486199 | G33: =IF(Assumption!M71=0,0,Assumption!M66/Assumption!M71) -> 0.72450916 | H33: =IF(Assumption!N71=0,0,Assumption!N66/Assumption!N71) -> 0.70471246 | I33: =IF(Assumption!O71=0,0,Assumption!O66/Assumption!O71) -> 0.68545669 | J33: =IF(Assumption!P71=0,0,Assumption!P66/Assumption!P71) -> 0.66672707
A34: Debt/equity | B34: =IF(Assumption!H47=0,0,Assumption!H49/Assumption!H47) -> 0.095530767 | C34: =IF(Assumption!I47=0,0,Assumption!I49/Assumption!I47) -> 0.097895936 | D34: =IF(Assumption!J47=0,0,Assumption!J49/Assumption!J47) -> 0.11220802 | E34: =IF(Assumption!K47=0,0,Assumption!K49/Assumption!K47) -> 0.05101781 | F34: =IF(Assumption!L47=0,0,Assumption!L49/Assumption!L47) -> 3.1824468e-05 | G34: =IF(Assumption!M47=0,0,Assumption!M49/Assumption!M47) -> 1.9378268e-08 | H34: =IF(Assumption!N47=0,0,Assumption!N49/Assumption!N47) -> 1.1799518e-11 | I34: =IF(Assumption!O47=0,0,Assumption!O49/Assumption!O47) -> 7.1847822e-15 | J34: =IF(Assumption!P47=0,0,Assumption!P49/Assumption!P47) -> 4.3748476e-18
A35: Interest Coverage ratio | B35: =IF(Assumption!H19=0,0,Assumption!H17/Assumption!H19) -> 100.75736 | C35: =IF(Assumption!I19=0,0,Assumption!I17/Assumption!I19) -> 40.369204 | D35: =IF(Assumption!J19=0,0,Assumption!J17/Assumption!J19) -> 24.483855 | E35: =IF(Assumption!K19=0,0,Assumption!K17/Assumption!K19) -> 18.622816 | F35: =IF(Assumption!L19=0,0,Assumption!L17/Assumption!L19) -> 13.452 | G35: =IF(Assumption!M19=0,0,Assumption!M17/Assumption!M19) -> 9.716914 | H35: =IF(Assumption!N19=0,0,Assumption!N17/Assumption!N19) -> 7.0189131 | I35: =IF(Assumption!O19=0,0,Assumption!O17/Assumption!O19) -> 5.0700398 | J35: =IF(Assumption!P19=0,0,Assumption!P17/Assumption!P19) -> 3.6622912

Sheet key ratio forcasted
B1: Ratio Forcasted
A3: INR Cr. | B3: 2026 | C3: 2027 | D3: 2028 | E3: 2029 | F3: 2030
A4: Operating Income | B4: ='financial satement'!L22 -> 1625.9091 | C4: ='financial satement'!M22 -> 1642.8425 | D4: ='financial satement'!N22 -> 1653.265 | E4: ='financial satement'!O22 -> 1655.955 | F4: ='financial satement'!P22 -> 1649.5121
A5: EBIT Growth | B5: =IF('financial satement'!K22=0,0,('financial satement'!L22-'financial satement'!K22)/'financial satement'!K22) -> -0.15353383 | C5: =IF('financial satement'!L22=0,0,('financial satement'!M22-'financial satement'!L22)/'financial satement'!L22) -> 0.010414722 | D5: =IF('financial satement'!M22=0,0,('financial satement'!N22-'financial satement'!M22)/'financial satement'!M22) -> 0.0063441834 | E5: =IF('financial satement'!N22=0,0,('financial satement'!O22-'financial satement'!N22)/'financial satement'!N22) -> 0.0016270506 | F5: =IF('financial satement'!O22=0,0,('financial satement'!P22-'financial satement'!O22)/'financial satement'!O22) -> -0.0038907313
A6: EBITDA | B6: ='financial satement'!L19 -> 1914.6734 | C6: ='financial satement'!M19 -> 1975.1457 | D6: ='financial satement'!N19 -> 2035.6716 | E6: ='financial satement'!O19 -> 2096.0194 | F6: ='financial satement'!P19 -> 2155.9278
A7: EBITDA Margin (%) | B7: =IF('financial satement'!L7=0,0,'financial satement'!L19/'financial satement'!L7) -> 0.19924008 | C7: =IF('financial satement'!M7=0,0,'financial satement'!M19/'financial satement'!M7) -> 0.19400118 | D7: =IF('financial satement'!N7=0,0,'financial satement'!N19/'financial satement'!N7) -> 0.18872796 | E7: =IF('financial satement'!O7=0,0,'financial satement'!O19/'financial satement'!O7) -> 0.18342017 | F7: =IF('financial satement'!P7=0,0,'financial satement'!P19/'financial satement'!P7) -> 0.17807759
A8: Net Income | B8: ='financial satement'!L29 -> 1405.0164 | C8: ='financial satement'!M29 -> 930.9956 | D8: ='financial satement'!N29 -> -1934.113 | E8: ='financial satement'!O29 -> -20165.81 | F8: ='financial satement'!P29 -> -138017.6
A9: EPS | B9: =IF('financial satement'!L38=0,0,'financial satement'!L29/'financial satement'!L38) -> 7.9289865 | C9: =IF('financial satement'!M38=0,0,'financial satement'!M29/'financial satement'!M38) -> 5.2539255 | D9: =IF('financial satement'!N38=0,0,'financial satement'!N29/'financial satement'!N38) -> -10.914859 | E9: =IF('financial satement'!O38=0,0,'financial satement'!O29/'financial satement'!O38) -> -113.80254 | F9: =IF('financial satement'!P38=0,0,'financial satement'!P29/'financial satement'!P38) -> -778.88035
A10: EPS Growth (%) | B10: =IF(B9=0,0,(B9-'financial satement'!K30)/'financial satement'!K30) -> 0.0011346625 | C10: =IF(B9=0,0,(C9-B9)/B9) -> -0.33737742 | D10: =IF(C9=0,0,(D9-C9)/C9) -> -3.0774674 | E10: =IF(D9=0,0,(E9-D9)/D9) -> 9.4263869 | F10: =IF(E9=0,0,(F9-E9)/E9) -> 5.8441385
A11: Dividend yield (%) | B11: =IF(B9=0,0,IF('financial satement'!L38=0,0,('financial satement'!L31/'financial satement'!L38)/B9)) -> 0 | C11: =IF(C9=0,0,IF('financial satement'!M38=0,0,('financial satement'!M31/'financial satement'!M38)/C9)) -> 0 | D11: =IF(D9=0,0,IF('financial satement'!N38=0,0,('financial satement'!N31/'financial satement'!N38)/D9)) -> 0 | E11: =IF(E9=0,0,IF('financial satement'!O38=0,0,('financial satement'!O31/'financial satement'!O38)/E9)) -> 0 | F11: =IF(F9=0,0,IF('financial satement'!P38=0,0,('financial satement'!P31/'financial satement'!P38)/F9)) -> 0
A12: ROCE (%) | B12: =IF(('financial satement'!L78-'financial satement'!L54)=0,0,'financial satement'!L22/('financial satement'!L78-'financial satement'!L54)) -> 0.35302079 | C12: =IF(('financial satement'!M78-'financial satement'!M54)=0,0,'financial satement'!M22/('financial satement'!M78-'financial satement'!M54)) -> 0.3814889 | D12: =IF(('financial satement'!N78-'financial satement'!N54)=0,0,'financial satement'!N22/('financial satement'!N78-'financial satement'!N54)) -> 0.41775559 | E12: =IF(('financial satement'!O78-'financial satement'!O54)=0,0,'financial satement'!O22/('financial satement'!O78-'financial satement'!O54)) -> 0.46607525 | F12: =IF(('financial satement'!P78-'financial satement'!P54)=0,0,'financial satement'!P22/('financial satement'!P78-'financial satement'!P54)) -> 0.53449676
A13: ROE (%) | B13: =IF('financial satement'!L41=0,0,'financial satement'!L29/'financial satement'!L41) -> 8.1825192e-05 | C13: =IF('financial satement'!M41=0,0,'financial satement'!M29/'financial satement'!M41) -> 2.2880725e-08 | D13: =IF('financial satement'!N41=0,0,'financial satement'!N29/'financial satement'!N41) -> -2.0059312e-11 | E13: =IF('financial satement'!O41=0,0,'financial satement'!O29/'financial satement'!O41) -> -8.8259593e-14 | F13: =IF('financial satement'!P41=0,0,'financial satement'!P29/'financial satement'!P41) -> -2.5491345e-16
A14: PE | B14: =IF(B9=0,0,('financial satement'!L41/'financial satement'!L38)/B9) -> 12221.175 | C14: =IF(C9=0,0,('financial satement'!M41/'financial satement'!M38)/C9) -> 43704908 | D14: =IF(D9=0,0,('financial satement'!N41/'financial satement'!N38)/D9) -> -4.9852157e+10 | E14: =IF(E9=0,0,('financial satement'!O41/'financial satement'!O38)/E9) -> -1.1330213e+13 | F14: =IF(F9=0,0,('financial satement'!P41/'financial satement'!P38)/F9) -> -3.9229001e+15
A15: P/BV | B15: =IF('financial satement'!L41=0,0,B14*B13) -> 1 | C15: =IF('financial satement'!M41=0,0,C14*C13) -> 1 | D15: =IF('financial satement'!N41=0,0,D14*D13) -> 1 | E15: =IF('financial satement'!O41=0,0,E14*E13) -> 1 | F15: =IF('financial satement'!P41=0,0,F14*F13) -> 1

Sheet Hmodel
B3: H model
B5: R | C5: 0.13 | E5: Phase 1 | F5: =(C8*C9*(C6-C7))/(C5-C7) -> 411.42857
B6: Gh | C6: 0.18 | E6: P2 | F6: =C8*(1+C7)/(C5-C7) -> 726.85714
B7: Gs | C7: 0.06 | F7: =SUM(F5:F6) -> 1138.2857
B8: Divident | C8: 48
B9: H | C9: 5 | E9: =F7 -> 1138.2857 | F9: 0.1 | G9: 0.11 | H9: 0.12 | I9: 0.14 | J9: 0.15 | K9: 0.16 | L9: 0.18 | M9: 0.2
E10: 0.18 | F10: 1992 | G10: 1593.6 | H10: 1328 | I10: 996 | J10: 885.33333 | K10: 796.8 | L10: 664 | M10: 569.14286
E11: 0.15 | F11: 1812 | G11: 1449.6 | H11: 1208 | I11: 906 | J11: 805.33333 | K11: 724.8 | L11: 604 | M11: 517.71429
E12: 0.12 | F12: 1632 | G12: 1305.6 | H12: 1088 | I12: 816 | J12: 725.33333 | K12: 652.8 | L12: 544 | M12: 466.28571
E13: 0.1 | F13: 1512 | G13: 1209.6 | H13: 1008 | I13: 756 | J13: 672 | K13: 604.8 | L13: 504 | M13: 432
E14: 0.08 | F14: 1392 | G14: 1113.6 | H14: 928 | I14: 696 | J14: 618.66667 | K14: 556.8 | L14: 464 | M14: 397.71429
E15: 0.07 | F15: 1332 | G15: 1065.6 | H15: 888 | I15: 666 | J15: 592 | K15: 532.8 | L15: 444 | M15: 380.57143
E16: 0.05 | F16: 1212 | G16: 969.6 | H16: 808 | I16: 606 | J16: 538.66667 | K16: 484.8 | L16: 404 | M16: 346.28571
A18: Three Stage
B20: Divident | C20: 5
B21: HGP | C21: 4
B22: Growth rate | C22: 0.3
B23: Rate | C23: 0.15 | E23: Phase 1
F24: 1 | G24: 2 | H24: 3 | I24: 4
E25: Expected | F25: =C20*(1+C22) -> 6.5 | G25: =F25*(1+C22) -> 8.45 | H25: =G25*(1+$C$22) -> 10.985 | I25: =H25*(1+$C$22) -> 14.2805
E26: Discount | F26: =F25/(1+C23^F24) -> 5.6521739
F27: =SUM(F26:I26) -> 5.6521739
E28: Phase 2
F29: 5 | G29: 6 | H29: 7 | I29: 8
F30: 0.25 | G30: 0.2 | H30: 0.15 | I30: 0.1
E31: Expected | F31: =I25*(1+F30) -> 17.850625 | G31: =F31*(1+G30) -> 21.42075 | H31: =G31*(1+H30) -> 24.633862 | I31: =H31*(1+I30) -> 27.097249
E32: Discount | F32: =F31/(1+$C$23)^F29 -> 8.8749155 | G32: =G31/(1+$C$23)^G29 -> 9.2607814 | H32: =H31/(1+$C$23)^H29 -> 9.2607814 | I32: =I31/(1+$C$23)^I29 -> 8.8581387
F33: =SUM(F32:I32) -> 36.254617
E34: Phase 3
F36: 9 | G36: 10 | H36: 11 | I36: 12
E37: Expected | F37: =I31*(1+C23) -> 31.161836
E38: Terminal Value | F38: =F37/(C23-C20) -> -6.4251208
E39: Discount | F39: =F38/1+C23 -> -6.2751208
